{
  "autoplayBgm": true,
  "autoplayBgs": true,
  "battleback1Name": "",
  "battleback2Name": "",
  "bgm": { "name": "", "pan": 0, "pitch": 100, "volume": 90 },
  "bgs": { "name": "", "pan": 0, "pitch": 100, "volume": 90 },
  "disableDashing": false,
  "displayName": "",
  "encounterList": [],
  "encounterStep": 30,
  "height": 10,
  "note": "",
  "parallaxLoopX": false,
  "parallaxLoopY": false,
  "parallaxName": "",
  "parallaxShow": true,
  "parallaxSx": 0,
  "parallaxSy": 0,
  "scrollType": 0,
  "specifyBattleback": false,
  "tilesetId": 3,
  "width": 15,
  "data": [
    1560, 1560, 1560, 1560, 1560, 1560, 1560, 1560, 1560, 1560, 1560, 1560,
    1560, 1560, 1560, 1560, 1560, 1560, 1560, 1560, 1560, 1560, 1560, 1560,
    1560, 1560, 1560, 1560, 1560, 1560, 1560, 3234, 3220, 3220, 3220, 3220,
    3220, 3236, 1560, 3234, 3220, 3220, 3220, 3236, 1560, 1560, 3216, 3200,
    3200, 3200, 3200, 3200, 3224, 1560, 3216, 3200, 3200, 3200, 3224, 1560,
    1560, 3216, 3200, 3200, 3200, 3200, 3200, 3224, 1560, 3216, 3200, 3200,
    3200, 3224, 1560, 1560, 3240, 3228, 3228, 3228, 3228, 3212, 3238, 1560,
    3240, 3228, 3228, 3212, 3238, 1560, 1560, 1560, 1560, 1560, 1560, 1560,
    3232, 1560, 1560, 1560, 1560, 1560, 3232, 1560, 1560, 1560, 3234, 3220,
    3220, 3220, 3220, 3203, 3220, 3220, 3220, 3220, 3220, 3203, 3236, 1560,
    1560, 3240, 3228, 3228, 3228, 3228, 3228, 3228, 3228, 3228, 3228, 3228,
    3228, 3238, 1560, 1560, 1560, 1560, 1560, 1560, 1560, 1560, 1560, 1560,
    1560, 1560, 1560, 1560, 1560, 1560, 0, 0, 0, 0, 0, 0, 0, 0, 0, 0, 0, 0, 0,
    0, 0, 0, 0, 0, 0, 0, 0, 0, 0, 0, 0, 0, 0, 0, 0, 0, 0, 0, 0, 0, 0, 0, 0, 0,
    0, 0, 0, 0, 0, 0, 0, 0, 0, 0, 0, 0, 0, 0, 0, 0, 0, 0, 0, 0, 0, 0, 0, 0, 0,
    0, 0, 0, 0, 0, 0, 0, 0, 0, 0, 0, 0, 0, 0, 0, 0, 0, 0, 0, 0, 0, 0, 0, 0, 0,
    0, 0, 0, 0, 0, 0, 0, 0, 0, 0, 0, 0, 0, 0, 0, 0, 0, 0, 0, 0, 0, 0, 0, 0, 0,
    0, 0, 0, 0, 0, 0, 0, 0, 0, 0, 0, 0, 0, 0, 0, 0, 0, 0, 0, 0, 0, 0, 0, 0, 0,
    0, 0, 0, 0, 0, 0, 0, 0, 0, 0, 0, 0, 0, 0, 0, 0, 0, 0, 0, 0, 0, 0, 0, 0, 0,
    0, 0, 0, 0, 0, 0, 0, 0, 0, 0, 0, 0, 0, 0, 0, 0, 0, 0, 0, 0, 0, 0, 0, 0, 0,
    0, 0, 0, 0, 0, 0, 0, 0, 0, 0, 0, 0, 0, 0, 0, 0, 0, 0, 0, 0, 0, 0, 0, 0, 0,
    0, 0, 0, 0, 0, 0, 0, 250, 250, 0, 0, 0, 0, 0, 0, 0, 0, 0, 0, 0, 0, 0, 0,
    235, 0, 0, 0, 0, 0, 0, 0, 0, 0, 0, 0, 0, 0, 0, 0, 0, 0, 0, 0, 0, 0, 0, 0, 0,
    0, 0, 0, 0, 0, 0, 0, 0, 0, 0, 0, 0, 0, 0, 0, 0, 0, 0, 0, 0, 0, 0, 0, 0, 0,
    0, 0, 0, 0, 0, 0, 0, 0, 0, 0, 0, 0, 0, 0, 0, 0, 0, 0, 0, 18, 0, 0, 0, 0, 0,
    0, 0, 228, 0, 0, 50, 0, 0, 0, 26, 54, 55, 0, 0, 0, 0, 0, 236, 0, 0, 58, 80,
    0, 0, 0, 62, 63, 0, 0, 0, 0, 0, 0, 0, 0, 0, 88, 0, 0, 108, 0, 0, 228, 0,
    242, 242, 0, 202, 0, 0, 0, 0, 0, 0, 0, 0, 0, 236, 0, 226, 227, 0, 201, 0, 0,
    0, 0, 0, 0, 0, 0, 0, 0, 0, 234, 228, 0, 201, 0, 0, 0, 0, 0, 0, 0, 0, 0, 0,
    0, 0, 0, 0, 0, 0, 0, 0, 0, 0, 0, 0, 0, 224, 224, 0, 0, 0, 0, 224, 0, 0, 11,
    0, 0, 0, 224, 0, 0, 0, 0, 224, 224, 0, 224, 0, 0, 0, 0, 0, 0, 0, 0, 0, 0, 0,
    0, 0, 0, 0, 0, 0, 0, 0, 0, 0, 0, 0, 0, 0, 0, 0, 0, 0, 0, 0, 0, 0, 0, 0, 0,
    0, 0, 0, 0, 0, 0, 0, 0, 0, 0, 0, 0, 0, 0, 0, 0, 0, 0, 0, 0, 0, 0, 0, 0, 0,
    0, 0, 0, 0, 0, 0, 0, 0, 0, 0, 0, 0, 0, 0, 0, 0, 0, 0, 0, 0, 0, 0, 0, 0, 0,
    0, 0, 0, 0, 0, 0, 0, 0, 0, 0, 0, 0, 0, 0, 0, 0, 0, 0, 0, 0, 0, 0, 0, 0, 0,
    0, 0, 0, 0, 0, 0, 0, 0, 0, 0, 0, 0, 0, 0, 0, 0, 0, 0, 0, 0, 0, 0, 0, 0, 0,
    0, 0, 0, 0, 0, 0, 0, 0, 0, 0, 0, 0, 0, 0, 0, 0, 0, 0, 0, 0, 0, 0, 0, 0, 0,
    0, 0, 0, 0, 0, 0, 0, 0, 0, 0, 0, 0, 0, 0, 0, 0, 0, 0, 0, 0, 0, 0, 0, 0, 0,
    0, 0, 0, 0, 0, 0, 0, 0, 0, 0, 0, 0, 0, 0, 0, 0, 0, 0, 0, 0, 0, 0, 0, 0, 0,
    0, 0, 0, 0, 0, 0, 0, 0, 0, 0, 0, 0, 0, 0, 0, 0, 0, 0, 0, 0, 0, 0, 0, 0, 0,
    0, 0, 0, 0, 0, 0, 0, 0, 0, 0, 0, 0, 0, 0, 0, 0, 0, 0, 0, 0, 0, 0, 0, 0, 0,
    0, 0, 0, 0, 0, 0, 0, 0, 0, 0, 0, 0, 0, 0, 0, 0, 0, 0, 0, 0, 0, 0, 0, 0, 0,
    0, 0, 0, 0, 0, 0, 0, 0, 0, 0, 0, 0, 0, 0, 0, 0, 0, 0, 0, 0, 0, 0, 0, 0, 0,
    0, 0, 0, 0, 0
  ],
  "events": [
    null,
    {
      "id": 1,
      "name": "EV001",
      "note": "",
      "pages": [
        {
          "conditions": {
            "actorId": 1,
            "actorValid": false,
            "itemId": 1,
            "itemValid": false,
            "selfSwitchCh": "A",
            "selfSwitchValid": false,
            "switch1Id": 1,
            "switch1Valid": false,
            "switch2Id": 1,
            "switch2Valid": false,
            "variableId": 1,
            "variableValid": false,
            "variableValue": 0
          },
          "directionFix": false,
          "image": {
            "characterIndex": 0,
            "characterName": "",
            "direction": 2,
            "pattern": 0,
            "tileId": 0
          },
          "list": [
            {
              "code": 250,
              "indent": 0,
              "parameters": [
                { "name": "Move1", "volume": 90, "pitch": 100, "pan": 0 }
              ]
            },
            { "code": 201, "indent": 0, "parameters": [0, 13, 2, 8, 6, 0] },
            {
              "code": 223,
              "indent": 0,
              "parameters": [[-68, -68, 0, 68], 1, true]
            },
            { "code": 0, "indent": 0, "parameters": [] }
          ],
          "moveFrequency": 3,
          "moveRoute": {
            "list": [{ "code": 0, "parameters": [] }],
            "repeat": true,
            "skippable": false,
            "wait": false
          },
          "moveSpeed": 3,
          "moveType": 0,
          "priorityType": 0,
          "stepAnime": false,
          "through": false,
          "trigger": 1,
          "walkAnime": true
        }
      ],
      "x": 1,
      "y": 8
    },
    {
      "id": 2,
      "name": "ライト",
      "note": "",
      "pages": [
        {
          "conditions": {
            "actorId": 1,
            "actorValid": false,
            "itemId": 1,
            "itemValid": false,
            "selfSwitchCh": "A",
            "selfSwitchValid": false,
            "switch1Id": 1,
            "switch1Valid": false,
            "switch2Id": 1,
            "switch2Valid": false,
            "variableId": 1,
            "variableValid": false,
            "variableValue": 0
          },
          "directionFix": false,
          "image": {
            "tileId": 0,
            "characterName": "sinnyuu",
            "direction": 6,
            "pattern": 1,
            "characterIndex": 0
          },
          "list": [{ "code": 0, "indent": 0, "parameters": [] }],
          "moveFrequency": 3,
          "moveRoute": {
            "list": [{ "code": 0, "parameters": [] }],
            "repeat": true,
            "skippable": false,
            "wait": false
          },
          "moveSpeed": 3,
          "moveType": 0,
          "priorityType": 1,
          "stepAnime": false,
          "through": false,
          "trigger": 0,
          "walkAnime": true
        }
      ],
      "x": 2,
      "y": 3
    },
    {
      "id": 3,
      "name": "EV003",
      "note": "",
      "pages": [
        {
          "conditions": {
            "actorId": 1,
            "actorValid": false,
            "itemId": 1,
            "itemValid": false,
            "selfSwitchCh": "A",
            "selfSwitchValid": false,
            "switch1Id": 1,
            "switch1Valid": false,
            "switch2Id": 1,
            "switch2Valid": false,
            "variableId": 1,
            "variableValid": false,
            "variableValue": 0
          },
          "directionFix": false,
          "image": {
            "characterIndex": 0,
            "characterName": "",
            "direction": 2,
            "pattern": 0,
            "tileId": 0
          },
          "list": [
            { "code": 101, "indent": 0, "parameters": ["hiroin2", 0, 1, 2] },
            { "code": 401, "indent": 0, "parameters": ["【Margaret】"] },
            {
              "code": 401,
              "indent": 0,
              "parameters": [
                "After parting ways with the two of them, I took a little time before\nheading to Light's house."
              ]
            },
            {
              "code": 250,
              "indent": 0,
              "parameters": [
                { "name": "Move5", "volume": 60, "pitch": 100, "pan": 0 }
              ]
            },
            { "code": 101, "indent": 0, "parameters": ["hiroin2", 0, 1, 2] },
            { "code": 401, "indent": 0, "parameters": ["【Margaret】"] },
            {
              "code": 401,
              "indent": 0,
              "parameters": [
                "Earlier, Light seemed strange, so if my guess is correct, he will now\nbe comforting himself."
              ]
            },
            { "code": 101, "indent": 0, "parameters": ["sinn", 5, 0, 2] },
            { "code": 401, "indent": 0, "parameters": ["【Light】"] },
            { "code": 401, "indent": 0, "parameters": ["Hah...hah..."] },
            { "code": 101, "indent": 0, "parameters": ["hiroin2", 0, 1, 2] },
            { "code": 401, "indent": 0, "parameters": ["【Margaret】"] },
            {
              "code": 401,
              "indent": 0,
              "parameters": [
                "When I peeked into the room, as expected, the act had already begun."
              ]
            },
            { "code": 101, "indent": 0, "parameters": ["hiroin2", 0, 1, 2] },
            { "code": 401, "indent": 0, "parameters": ["【Margaret】"] },
            {
              "code": 401,
              "indent": 0,
              "parameters": [
                "Right now, I know the technique to help with that... *sigh*"
              ]
            },
            { "code": 101, "indent": 0, "parameters": ["hiroin2", 0, 1, 2] },
            { "code": 401, "indent": 0, "parameters": ["【Margaret】"] },
            {
              "code": 401,
              "indent": 0,
              "parameters": ["I took a deep breath and entered the room."]
            },
            {
              "code": 250,
              "indent": 0,
              "parameters": [
                { "name": "Door1", "volume": 40, "pitch": 100, "pan": 0 }
              ]
            },
            { "code": 222, "indent": 0, "parameters": [] },
            { "code": 213, "indent": 0, "parameters": [2, 1, false] },
            { "code": 101, "indent": 0, "parameters": ["sinn", 5, 0, 2] },
            { "code": 401, "indent": 0, "parameters": ["【Light】"] },
            {
              "code": 401,
              "indent": 0,
              "parameters": [
                "Margaret? Why are you here...!? Oh, no, this is..."
              ]
            },
            { "code": 213, "indent": 0, "parameters": [2, 11, false] },
            { "code": 101, "indent": 0, "parameters": ["hiroin2", 0, 1, 2] },
            { "code": 401, "indent": 0, "parameters": ["【Margaret】"] },
            {
              "code": 401,
              "indent": 0,
              "parameters": [
                "Light, flustered while exposing his erect dick, was a little amusing,\nbut..."
              ]
            },
            { "code": 101, "indent": 0, "parameters": ["hiroin2", 0, 1, 2] },
            { "code": 401, "indent": 0, "parameters": ["【Margaret】"] },
            {
              "code": 401,
              "indent": 0,
              "parameters": ["I didn't come here tonight to see that."]
            },
            { "code": 101, "indent": 0, "parameters": ["hiroin2", 0, 0, 2] },
            { "code": 401, "indent": 0, "parameters": ["【Margaret】"] },
            {
              "code": 401,
              "indent": 0,
              "parameters": ["That dick... it's because of the curse, right?"]
            },
            { "code": 101, "indent": 0, "parameters": ["sinn", 5, 0, 2] },
            { "code": 401, "indent": 0, "parameters": ["【Light】"] },
            {
              "code": 401,
              "indent": 0,
              "parameters": [
                "...Is that so? Who did you hear that from? Azami- san, perhaps..."
              ]
            },
            { "code": 101, "indent": 0, "parameters": ["hiroin2", 0, 1, 2] },
            { "code": 401, "indent": 0, "parameters": ["【Margaret】"] },
            {
              "code": 401,
              "indent": 0,
              "parameters": [
                "I see, so Azami-san knows about this. It makes sense, since I relied\non Azami-san's care for a while after being cursed."
              ]
            },
            { "code": 101, "indent": 0, "parameters": ["hiroin2", 0, 0, 2] },
            { "code": 401, "indent": 0, "parameters": ["【Margaret】"] },
            {
              "code": 401,
              "indent": 0,
              "parameters": [
                "What's the point of continuing this? It doesn't matter anymore."
              ]
            },
            { "code": 101, "indent": 0, "parameters": ["sinn", 5, 0, 2] },
            { "code": 401, "indent": 0, "parameters": ["【Light】"] },
            {
              "code": 401,
              "indent": 0,
              "parameters": [
                "It can't be helped... I just can't control it. If I don't do this, I\nfeel like I'll go insane."
              ]
            },
            { "code": 101, "indent": 0, "parameters": ["hiroin2", 0, 0, 2] },
            { "code": 401, "indent": 0, "parameters": ["【Margaret】"] },
            {
              "code": 401,
              "indent": 0,
              "parameters": [
                "If I said I can do something about that, would you believe me?"
              ]
            },
            { "code": 213, "indent": 0, "parameters": [2, 1, false] },
            { "code": 101, "indent": 0, "parameters": ["sinn", 5, 0, 2] },
            { "code": 401, "indent": 0, "parameters": ["【Light】"] },
            {
              "code": 401,
              "indent": 0,
              "parameters": [
                "Is there really a way!? Please, tell me right away!"
              ]
            },
            { "code": 101, "indent": 0, "parameters": ["hiroin2", 0, 0, 2] },
            { "code": 401, "indent": 0, "parameters": ["【Margaret】"] },
            {
              "code": 401,
              "indent": 0,
              "parameters": [
                "First, could you lie down on the bed and close your eyes?"
              ]
            },
            { "code": 101, "indent": 0, "parameters": ["sinn", 5, 0, 2] },
            { "code": 401, "indent": 0, "parameters": ["【Light】"] },
            {
              "code": 401,
              "indent": 0,
              "parameters": ["I understand. Margaret, you really saved me."]
            },
            { "code": 221, "indent": 0, "parameters": [] },
            {
              "code": 205,
              "indent": 0,
              "parameters": [
                2,
                {
                  "list": [
                    { "code": 37, "indent": null },
                    { "code": 29, "parameters": [6], "indent": null },
                    { "code": 4, "indent": null },
                    { "code": 16, "indent": null },
                    { "code": 0 }
                  ],
                  "repeat": false,
                  "skippable": false,
                  "wait": false
                }
              ]
            },
            {
              "code": 505,
              "indent": 0,
              "parameters": [{ "code": 37, "indent": null }]
            },
            {
              "code": 505,
              "indent": 0,
              "parameters": [{ "code": 29, "parameters": [6], "indent": null }]
            },
            {
              "code": 505,
              "indent": 0,
              "parameters": [{ "code": 4, "indent": null }]
            },
            {
              "code": 505,
              "indent": 0,
              "parameters": [{ "code": 16, "indent": null }]
            },
            { "code": 356, "indent": 0, "parameters": ["HALF_MOVE_ENABLE"] },
            {
              "code": 205,
              "indent": 0,
              "parameters": [
                4,
                {
                  "list": [
                    { "code": 37, "indent": null },
                    { "code": 29, "parameters": [6], "indent": null },
                    { "code": 2, "indent": null },
                    { "code": 2, "indent": null },
                    { "code": 4, "indent": null },
                    { "code": 19, "indent": null },
                    { "code": 0 }
                  ],
                  "repeat": false,
                  "skippable": false,
                  "wait": true
                }
              ]
            },
            {
              "code": 505,
              "indent": 0,
              "parameters": [{ "code": 37, "indent": null }]
            },
            {
              "code": 505,
              "indent": 0,
              "parameters": [{ "code": 29, "parameters": [6], "indent": null }]
            },
            {
              "code": 505,
              "indent": 0,
              "parameters": [{ "code": 2, "indent": null }]
            },
            {
              "code": 505,
              "indent": 0,
              "parameters": [{ "code": 2, "indent": null }]
            },
            {
              "code": 505,
              "indent": 0,
              "parameters": [{ "code": 4, "indent": null }]
            },
            {
              "code": 505,
              "indent": 0,
              "parameters": [{ "code": 19, "indent": null }]
            },
            { "code": 101, "indent": 0, "parameters": ["hiroin2", 2, 1, 2] },
            { "code": 401, "indent": 0, "parameters": ["【Margaret】"] },
            {
              "code": 401,
              "indent": 0,
              "parameters": [
                "It feels like I'm deceiving you in a way, but if it ultimately\nresolves the situation, it's not necessarily wrong..."
              ]
            },
            {
              "code": 250,
              "indent": 0,
              "parameters": [
                { "name": "衣擦音05", "volume": 90, "pitch": 100, "pan": 0 }
              ]
            },
            { "code": 230, "indent": 0, "parameters": [20] },
            {
              "code": 250,
              "indent": 0,
              "parameters": [
                { "name": "ベッド軋短音", "volume": 30, "pitch": 90, "pan": 0 }
              ]
            },
            { "code": 101, "indent": 0, "parameters": ["hiroin2", 0, 1, 2] },
            { "code": 401, "indent": 0, "parameters": ["【Margaret】"] },
            {
              "code": 401,
              "indent": 0,
              "parameters": [
                "Slowly straddle over Light and put your hand on the familiar dick."
              ]
            },
            {
              "code": 241,
              "indent": 0,
              "parameters": [
                { "name": "Scene7", "volume": 70, "pitch": 100, "pan": 0 }
              ]
            },
            {
              "code": 231,
              "indent": 0,
              "parameters": [1, "hiro2 sin 1-1", 0, 0, 0, 0, 100, 100, 255, 0]
            },
            { "code": 222, "indent": 0, "parameters": [] },
            { "code": 101, "indent": 0, "parameters": ["", 5, 0, 2] },
            { "code": 401, "indent": 0, "parameters": ["【Light】"] },
            {
              "code": 401,
              "indent": 0,
              "parameters": ["Hey, Margaret! What are you doing?!"]
            },
            { "code": 101, "indent": 0, "parameters": ["", 0, 0, 2] },
            { "code": 401, "indent": 0, "parameters": ["【Margaret】"] },
            {
              "code": 401,
              "indent": 0,
              "parameters": ["What... are you holding the dick?"]
            },
            { "code": 101, "indent": 0, "parameters": ["", 5, 0, 2] },
            { "code": 401, "indent": 0, "parameters": ["【Light】"] },
            {
              "code": 401,
              "indent": 0,
              "parameters": ["It's not like that! ...!"]
            },
            {
              "code": 245,
              "indent": 0,
              "parameters": [
                {
                  "name": "擦_濡02中速(loop)",
                  "volume": 30,
                  "pitch": 100,
                  "pan": 0
                }
              ]
            },
            { "code": 101, "indent": 0, "parameters": ["", 2, 1, 2] },
            { "code": 401, "indent": 0, "parameters": ["【Margaret】"] },
            {
              "code": 401,
              "indent": 0,
              "parameters": [
                "I find it bothersome to explain, so I start handling the dick in\nsilence."
              ]
            },
            { "code": 101, "indent": 0, "parameters": ["", 0, 1, 2] },
            { "code": 401, "indent": 0, "parameters": ["【Margaret】"] },
            {
              "code": 401,
              "indent": 0,
              "parameters": [
                "In that state, I couldn't tell what Light's expression was because I\nhad fainted before, but this time it's different as I gaze silently at\nLight's expression."
              ]
            },
            { "code": 101, "indent": 0, "parameters": ["", 0, 1, 2] },
            { "code": 401, "indent": 0, "parameters": ["【Margaret】"] },
            {
              "code": 401,
              "indent": 0,
              "parameters": [
                "As soon as I grasped the dick, his expression tightened... It's quite\nobvious."
              ]
            },
            { "code": 101, "indent": 0, "parameters": ["", 5, 0, 2] },
            { "code": 401, "indent": 0, "parameters": ["【Light】"] },
            {
              "code": 401,
              "indent": 0,
              "parameters": ["Hey! This is... no good..."]
            },
            {
              "code": 231,
              "indent": 0,
              "parameters": [2, "hiro2 sin 1-2", 0, 0, 0, 0, 100, 100, 255, 0]
            },
            { "code": 235, "indent": 0, "parameters": [1] },
            { "code": 101, "indent": 0, "parameters": ["", 2, 0, 2] },
            { "code": 401, "indent": 0, "parameters": ["【Margaret】"] },
            {
              "code": 401,
              "indent": 0,
              "parameters": [
                "You say that, but the precum is already coming out."
              ]
            },
            { "code": 101, "indent": 0, "parameters": ["", 2, 0, 2] },
            { "code": 401, "indent": 0, "parameters": ["【Margaret】"] },
            {
              "code": 401,
              "indent": 0,
              "parameters": ["...The body is honest"]
            },
            { "code": 101, "indent": 0, "parameters": ["", 0, 1, 2] },
            { "code": 401, "indent": 0, "parameters": ["【Margaret】"] },
            {
              "code": 401,
              "indent": 0,
              "parameters": [
                "By looking at the feeling and expression of the dick, I could tell how\nmuch Light is feeling right now as I took it in my hand."
              ]
            },
            { "code": 101, "indent": 0, "parameters": ["", 0, 1, 2] },
            { "code": 401, "indent": 0, "parameters": ["【Margaret】"] },
            {
              "code": 401,
              "indent": 0,
              "parameters": [
                "He'll probably ejaculate pitifully in less than 20 seconds."
              ]
            },
            { "code": 101, "indent": 0, "parameters": ["", 5, 0, 2] },
            { "code": 401, "indent": 0, "parameters": ["【Light】"] },
            {
              "code": 401,
              "indent": 0,
              "parameters": ["Hah... hah... right there... hnngh..."]
            },
            { "code": 101, "indent": 0, "parameters": ["", 2, 1, 2] },
            { "code": 401, "indent": 0, "parameters": ["【Margaret】"] },
            {
              "code": 401,
              "indent": 0,
              "parameters": [
                "The more I handle it, the more precum overflows from the dick."
              ]
            },
            { "code": 101, "indent": 0, "parameters": ["", 2, 0, 2] },
            { "code": 401, "indent": 0, "parameters": ["【Margaret】"] },
            {
              "code": 401,
              "indent": 0,
              "parameters": [
                "Look, don't hold back and ejaculate quickly without making a mess like\nthis."
              ]
            },
            { "code": 101, "indent": 0, "parameters": ["", 5, 0, 2] },
            { "code": 401, "indent": 0, "parameters": ["【Light】"] },
            {
              "code": 401,
              "indent": 0,
              "parameters": ["Margaret... stop... I can't take this... *grunt*"]
            },
            {
              "code": 231,
              "indent": 0,
              "parameters": [1, "hiro2 sin 1-4", 0, 0, 0, 0, 100, 100, 255, 0]
            },
            { "code": 235, "indent": 0, "parameters": [2] },
            { "code": 117, "indent": 0, "parameters": [4] },
            { "code": 101, "indent": 0, "parameters": ["", 0, 1, 2] },
            { "code": 401, "indent": 0, "parameters": ["【Margaret】"] },
            {
              "code": 401,
              "indent": 0,
              "parameters": [
                "16 seconds... It was pretty much as expected. This might be a little\nfun."
              ]
            },
            { "code": 101, "indent": 0, "parameters": ["", 2, 0, 2] },
            { "code": 401, "indent": 0, "parameters": ["【Margaret】"] },
            {
              "code": 401,
              "indent": 0,
              "parameters": ["...First, let's start with one round"]
            },
            { "code": 101, "indent": 0, "parameters": ["", 2, 0, 2] },
            { "code": 401, "indent": 0, "parameters": ["【Margaret】"] },
            {
              "code": 401,
              "indent": 0,
              "parameters": [
                "The dick is still twitching, unsatisfied. I'll make it ejaculate more\nfor you."
              ]
            },
            { "code": 101, "indent": 0, "parameters": ["", 5, 0, 2] },
            { "code": 401, "indent": 0, "parameters": ["【Light】"] },
            { "code": 401, "indent": 0, "parameters": ["Hah... hah..."] },
            { "code": 101, "indent": 0, "parameters": ["", 2, 1, 2] },
            { "code": 401, "indent": 0, "parameters": ["【Margaret】"] },
            {
              "code": 401,
              "indent": 0,
              "parameters": [
                "I'll handle the dick, which has become even slicker with semen, for\nyou."
              ]
            },
            { "code": 101, "indent": 0, "parameters": ["", 2, 1, 2] },
            { "code": 401, "indent": 0, "parameters": ["【Margaret】"] },
            {
              "code": 401,
              "indent": 0,
              "parameters": [
                "I think that Light's hesitance is due to his sense of reason, but it\nseems like his dick won't allow that."
              ]
            },
            { "code": 101, "indent": 0, "parameters": ["", 0, 1, 2] },
            { "code": 401, "indent": 0, "parameters": ["【Margaret】"] },
            {
              "code": 401,
              "indent": 0,
              "parameters": [
                "I handle the dick, making lewd squelching sounds as much as possible,\nand ask Light in a gentle voice."
              ]
            },
            { "code": 101, "indent": 0, "parameters": ["", 2, 0, 2] },
            { "code": 401, "indent": 0, "parameters": ["【Margaret】"] },
            {
              "code": 401,
              "indent": 0,
              "parameters": ["How does it feel, Light?"]
            },
            { "code": 101, "indent": 0, "parameters": ["", 5, 0, 2] },
            { "code": 401, "indent": 0, "parameters": ["【Light】"] },
            {
              "code": 401,
              "indent": 0,
              "parameters": ["Hah... that, kind of thing..."]
            },
            { "code": 101, "indent": 0, "parameters": ["", 2, 1, 2] },
            { "code": 401, "indent": 0, "parameters": ["【Margaret】"] },
            {
              "code": 401,
              "indent": 0,
              "parameters": [
                "...Even though it feels good, it seems like he's being stubborn."
              ]
            },
            { "code": 101, "indent": 0, "parameters": ["", 2, 0, 2] },
            { "code": 401, "indent": 0, "parameters": ["【Margaret】"] },
            {
              "code": 401,
              "indent": 0,
              "parameters": [
                "You're still not being honest? ...Well, if that's the case, then it's\nfine."
              ]
            },
            {
              "code": 245,
              "indent": 0,
              "parameters": [
                {
                  "name": "擦_濡03高速(loop)",
                  "volume": 60,
                  "pitch": 100,
                  "pan": 0
                }
              ]
            },
            { "code": 101, "indent": 0, "parameters": ["", 0, 1, 2] },
            { "code": 401, "indent": 0, "parameters": ["【Margaret】"] },
            {
              "code": 401,
              "indent": 0,
              "parameters": [
                "After giving Light a gentle smile, I firmly grip the dick and roughly\nhandle it."
              ]
            },
            { "code": 101, "indent": 0, "parameters": ["", 0, 1, 2] },
            { "code": 401, "indent": 0, "parameters": ["【Margaret】"] },
            {
              "code": 401,
              "indent": 0,
              "parameters": [
                "Light's dick is in a slightly special state, surely his sexual\nexcitement is higher than usual."
              ]
            },
            { "code": 101, "indent": 0, "parameters": ["", 0, 1, 2] },
            { "code": 401, "indent": 0, "parameters": ["【Margaret】"] },
            {
              "code": 401,
              "indent": 0,
              "parameters": [
                "If I give him a stronger stimulation than usual there's no way he can\nendure it."
              ]
            },
            { "code": 101, "indent": 0, "parameters": ["", 5, 0, 2] },
            { "code": 401, "indent": 0, "parameters": ["【Light】"] },
            {
              "code": 401,
              "indent": 0,
              "parameters": ["!?... No... if you do that much... ah...!"]
            },
            {
              "code": 231,
              "indent": 0,
              "parameters": [2, "hiro2 sin 1-7", 0, 0, 0, 0, 100, 100, 255, 0]
            },
            { "code": 235, "indent": 0, "parameters": [1] },
            { "code": 117, "indent": 0, "parameters": [4] },
            {
              "code": 245,
              "indent": 0,
              "parameters": [
                {
                  "name": "擦_濡01低速(loop)",
                  "volume": 60,
                  "pitch": 100,
                  "pan": 0
                }
              ]
            },
            { "code": 101, "indent": 0, "parameters": ["", 2, 1, 2] },
            { "code": 401, "indent": 0, "parameters": ["【Margaret】"] },
            {
              "code": 401,
              "indent": 0,
              "parameters": [
                "Just as I thought, when I put a little effort into it, he made a\npitiful voice and ejaculated immediately."
              ]
            },
            { "code": 101, "indent": 0, "parameters": ["", 0, 1, 2] },
            { "code": 401, "indent": 0, "parameters": ["【Margaret】"] },
            {
              "code": 401,
              "indent": 0,
              "parameters": [
                "I might be the one who knows Light's dick the best, and that makes me\nfeel a little proud."
              ]
            },
            { "code": 101, "indent": 0, "parameters": ["", 2, 0, 2] },
            { "code": 401, "indent": 0, "parameters": ["【Margaret】"] },
            {
              "code": 401,
              "indent": 0,
              "parameters": ["Does your dick feel good?"]
            },
            { "code": 101, "indent": 0, "parameters": ["", 5, 0, 2] },
            { "code": 401, "indent": 0, "parameters": ["【Light】"] },
            {
              "code": 401,
              "indent": 0,
              "parameters": [
                "Feels good... feels so good! So, please go a little easier on me...!"
              ]
            },
            { "code": 101, "indent": 0, "parameters": ["", 0, 1, 2] },
            { "code": 401, "indent": 0, "parameters": ["【Margaret】"] },
            {
              "code": 401,
              "indent": 0,
              "parameters": [
                "Light, with slightly bloodshot eyes, drools from his mouth."
              ]
            },
            { "code": 101, "indent": 0, "parameters": ["", 0, 1, 2] },
            { "code": 401, "indent": 0, "parameters": ["【Margaret】"] },
            {
              "code": 401,
              "indent": 0,
              "parameters": [
                "As I thought, this is abnormal, it's because of a terrifying curse...\nthat's why..."
              ]
            },
            { "code": 101, "indent": 0, "parameters": ["", 2, 0, 2] },
            { "code": 401, "indent": 0, "parameters": ["【Margaret】"] },
            {
              "code": 401,
              "indent": 0,
              "parameters": [
                "...I'll make you ejaculate again as a great reward."
              ]
            },
            { "code": 101, "indent": 0, "parameters": ["", 5, 0, 2] },
            { "code": 401, "indent": 0, "parameters": ["【Light】"] },
            {
              "code": 401,
              "indent": 0,
              "parameters": ["Huh!? ...Margaret? Wait, just a little...!"]
            },
            {
              "code": 245,
              "indent": 0,
              "parameters": [
                {
                  "name": "擦_濡03高速(loop)",
                  "volume": 60,
                  "pitch": 100,
                  "pan": 0
                }
              ]
            },
            { "code": 101, "indent": 0, "parameters": ["", 2, 1, 2] },
            { "code": 401, "indent": 0, "parameters": ["【Margaret】"] },
            {
              "code": 401,
              "indent": 0,
              "parameters": [
                "You may say various things with your mouth, but your dick is so\ntwitchy and seems so happy. Surely, this is the correct answer."
              ]
            },
            { "code": 101, "indent": 0, "parameters": ["", 2, 1, 2] },
            { "code": 401, "indent": 0, "parameters": ["【Margaret】"] },
            {
              "code": 401,
              "indent": 0,
              "parameters": [
                "If Light is suffering because of his sexual desire, then I should\nthoroughly remove that for him."
              ]
            },
            { "code": 101, "indent": 0, "parameters": ["", 2, 1, 2] },
            { "code": 401, "indent": 0, "parameters": ["【Margaret】"] },
            {
              "code": 401,
              "indent": 0,
              "parameters": [
                "She peered into Light's face once again and smiled sweetly."
              ]
            },
            { "code": 221, "indent": 0, "parameters": [] },
            { "code": 101, "indent": 0, "parameters": ["", 2, 0, 2] },
            { "code": 401, "indent": 0, "parameters": ["【Margaret】"] },
            {
              "code": 401,
              "indent": 0,
              "parameters": [
                "We're just getting started, so I'll let you ejaculate until you're\nsatisfied."
              ]
            },
            { "code": 101, "indent": 0, "parameters": ["", 5, 0, 2] },
            { "code": 401, "indent": 0, "parameters": ["【Light】"] },
            {
              "code": 401,
              "indent": 0,
              "parameters": ["Ha... ah... no, that's not good... hah..."]
            },
            { "code": 101, "indent": 0, "parameters": ["", 5, 0, 2] },
            { "code": 401, "indent": 0, "parameters": ["【Light】"] },
            {
              "code": 401,
              "indent": 0,
              "parameters": ["Ah... stop... feels good... ahh..."]
            },
            { "code": 242, "indent": 0, "parameters": [8] },
            { "code": 246, "indent": 0, "parameters": [8] },
            { "code": 101, "indent": 0, "parameters": ["", 0, 1, 2] },
            { "code": 401, "indent": 0, "parameters": ["..."] },
            { "code": 101, "indent": 0, "parameters": ["", 0, 1, 2] },
            { "code": 401, "indent": 0, "parameters": ["..."] },
            { "code": 230, "indent": 0, "parameters": [60] },
            { "code": 356, "indent": 0, "parameters": ["HALF_MOVE_DISABLE"] },
            { "code": 117, "indent": 0, "parameters": [7] },
            { "code": 117, "indent": 0, "parameters": [4] },
            { "code": 223, "indent": 0, "parameters": [[0, 0, 0, 0], 1, true] },
            { "code": 211, "indent": 0, "parameters": [1] },
            { "code": 117, "indent": 0, "parameters": [3] },
            { "code": 201, "indent": 0, "parameters": [0, 47, 10, 10, 2, 0] },
            { "code": 222, "indent": 0, "parameters": [] },
            { "code": 0, "indent": 0, "parameters": [] }
          ],
          "moveFrequency": 3,
          "moveRoute": {
            "list": [{ "code": 0, "parameters": [] }],
            "repeat": true,
            "skippable": false,
            "wait": false
          },
          "moveSpeed": 3,
          "moveType": 0,
          "priorityType": 0,
          "stepAnime": false,
          "through": false,
          "trigger": 3,
          "walkAnime": true
        }
      ],
      "x": 4,
      "y": 5
    },
    {
      "id": 4,
      "name": "ヒロイン",
      "note": "",
      "pages": [
        {
          "conditions": {
            "actorId": 1,
            "actorValid": false,
            "itemId": 1,
            "itemValid": false,
            "selfSwitchCh": "A",
            "selfSwitchValid": false,
            "switch1Id": 1,
            "switch1Valid": false,
            "switch2Id": 1,
            "switch2Valid": false,
            "variableId": 1,
            "variableValid": false,
            "variableValue": 0
          },
          "directionFix": false,
          "image": {
            "tileId": 0,
            "characterName": "hiro1",
            "direction": 4,
            "pattern": 1,
            "characterIndex": 4
          },
          "list": [{ "code": 0, "indent": 0, "parameters": [] }],
          "moveFrequency": 3,
          "moveRoute": {
            "list": [{ "code": 0, "parameters": [] }],
            "repeat": true,
            "skippable": false,
            "wait": false
          },
          "moveSpeed": 3,
          "moveType": 0,
          "priorityType": 1,
          "stepAnime": false,
          "through": false,
          "trigger": 0,
          "walkAnime": true
        }
      ],
      "x": 3,
      "y": 3
    },
    {
      "id": 5,
      "name": "ライトの部屋の扉",
      "note": "",
      "pages": [
        {
          "conditions": {
            "actorId": 1,
            "actorValid": false,
            "itemId": 1,
            "itemValid": false,
            "selfSwitchCh": "A",
            "selfSwitchValid": false,
            "switch1Id": 1,
            "switch1Valid": false,
            "switch2Id": 1,
            "switch2Valid": false,
            "variableId": 1,
            "variableValid": false,
            "variableValue": 0
          },
          "directionFix": false,
          "image": {
            "tileId": 0,
            "characterName": "!Door1",
            "direction": 2,
            "pattern": 0,
            "characterIndex": 0
          },
          "list": [{ "code": 0, "indent": 0, "parameters": [] }],
          "moveFrequency": 3,
          "moveRoute": {
            "list": [
              { "code": 31, "indent": null },
              { "code": 17, "indent": null },
              { "code": 16, "indent": null },
              { "code": 0, "parameters": [] }
            ],
            "repeat": false,
            "skippable": false,
            "wait": false
          },
          "moveSpeed": 4,
          "moveType": 0,
          "priorityType": 1,
          "stepAnime": true,
          "through": false,
          "trigger": 1,
          "walkAnime": true
        }
      ],
      "x": 6,
      "y": 6
    },
    {
      "id": 6,
      "name": "自宅",
      "note": "",
      "pages": [
        {
          "conditions": {
            "actorId": 1,
            "actorValid": false,
            "itemId": 1,
            "itemValid": false,
            "selfSwitchCh": "A",
            "selfSwitchValid": false,
            "switch1Id": 1,
            "switch1Valid": false,
            "switch2Id": 1,
            "switch2Valid": false,
            "variableId": 1,
            "variableValid": false,
            "variableValue": 0
          },
          "directionFix": false,
          "image": {
            "tileId": 0,
            "characterName": "!Door1",
            "direction": 2,
            "pattern": 0,
            "characterIndex": 0
          },
          "list": [
            {
              "code": 250,
              "indent": 0,
              "parameters": [
                { "name": "Key", "volume": 90, "pitch": 100, "pan": 0 }
              ]
            },
            { "code": 101, "indent": 0, "parameters": ["", 0, 1, 2] },
            {
              "code": 401,
              "indent": 0,
              "parameters": ["It seems the key is locked."]
            },
            { "code": 0, "indent": 0, "parameters": [] }
          ],
          "moveFrequency": 3,
          "moveRoute": {
            "list": [
              { "code": 31, "indent": null },
              { "code": 17, "indent": null },
              { "code": 16, "indent": null },
              { "code": 0, "parameters": [] }
            ],
            "repeat": false,
            "skippable": false,
            "wait": false
          },
          "moveSpeed": 4,
          "moveType": 0,
          "priorityType": 1,
          "stepAnime": true,
          "through": false,
          "trigger": 1,
          "walkAnime": true
        }
      ],
      "x": 12,
      "y": 6
    },
    {
      "id": 7,
      "name": "fesfsef",
      "note": "",
      "pages": [
        {
          "conditions": {
            "actorId": 1,
            "actorValid": false,
            "itemId": 1,
            "itemValid": false,
            "selfSwitchCh": "A",
            "selfSwitchValid": false,
            "switch1Id": 1,
            "switch1Valid": false,
            "switch2Id": 1,
            "switch2Valid": false,
            "variableId": 1,
            "variableValid": false,
            "variableValue": 0
          },
          "directionFix": false,
          "image": {
            "characterIndex": 0,
            "characterName": "",
            "direction": 2,
            "pattern": 0,
            "tileId": 0
          },
          "list": [{ "code": 0, "indent": 0, "parameters": [] }],
          "moveFrequency": 3,
          "moveRoute": {
            "list": [{ "code": 0, "parameters": [] }],
            "repeat": true,
            "skippable": false,
            "wait": false
          },
          "moveSpeed": 3,
          "moveType": 0,
          "priorityType": 0,
          "stepAnime": false,
          "through": false,
          "trigger": 0,
          "walkAnime": true
        }
      ],
      "x": 14,
      "y": 1
    },
    {
      "id": 8,
      "name": "rerere",
      "note": "",
      "pages": [
        {
          "conditions": {
            "actorId": 1,
            "actorValid": false,
            "itemId": 1,
            "itemValid": false,
            "selfSwitchCh": "A",
            "selfSwitchValid": false,
            "switch1Id": 1,
            "switch1Valid": false,
            "switch2Id": 1,
            "switch2Valid": false,
            "variableId": 1,
            "variableValid": false,
            "variableValue": 0
          },
          "directionFix": false,
          "image": {
            "characterIndex": 0,
            "characterName": "",
            "direction": 2,
            "pattern": 0,
            "tileId": 0
          },
          "list": [{ "code": 0, "indent": 0, "parameters": [] }],
          "moveFrequency": 3,
          "moveRoute": {
            "list": [{ "code": 0, "parameters": [] }],
            "repeat": true,
            "skippable": false,
            "wait": false
          },
          "moveSpeed": 3,
          "moveType": 0,
          "priorityType": 0,
          "stepAnime": false,
          "through": false,
          "trigger": 0,
          "walkAnime": true
        }
      ],
      "x": 8,
      "y": 4
    },
    null,
    null,
    null
  ]
}
