{
  "autoplayBgm": true,
  "autoplayBgs": true,
  "battleback1Name": "",
  "battleback2Name": "",
  "bgm": { "name": "", "pan": 0, "pitch": 100, "volume": 90 },
  "bgs": { "name": "", "pan": 0, "pitch": 100, "volume": 90 },
  "disableDashing": false,
  "displayName": "",
  "encounterList": [],
  "encounterStep": 30,
  "height": 20,
  "note": "",
  "parallaxLoopX": false,
  "parallaxLoopY": false,
  "parallaxName": "",
  "parallaxShow": true,
  "parallaxSx": 0,
  "parallaxSy": 0,
  "scrollType": 0,
  "specifyBattleback": false,
  "tilesetId": 3,
  "width": 30,
  "data": [
    0, 0, 0, 0, 0, 0, 0, 0, 0, 0, 0, 0, 0, 0, 0, 0, 0, 0, 0, 0, 0, 0, 0, 0, 0,
    0, 0, 0, 0, 0, 0, 0, 0, 0, 0, 0, 0, 0, 0, 0, 0, 0, 0, 0, 0, 0, 0, 0, 0, 0,
    0, 0, 0, 0, 0, 0, 0, 0, 0, 0, 0, 0, 0, 0, 0, 0, 0, 0, 0, 0, 0, 0, 0, 0, 0,
    0, 0, 0, 0, 0, 0, 0, 0, 0, 0, 0, 0, 0, 0, 0, 0, 0, 0, 0, 0, 0, 0, 0, 0, 0,
    0, 0, 0, 0, 0, 0, 0, 0, 0, 0, 0, 0, 0, 0, 0, 0, 0, 0, 0, 0, 0, 0, 0, 0, 0,
    0, 0, 0, 0, 0, 0, 0, 0, 0, 0, 0, 0, 0, 0, 0, 0, 0, 0, 0, 0, 0, 0, 0, 0, 0,
    0, 0, 0, 0, 0, 0, 0, 0, 1560, 1560, 1560, 1560, 1560, 1560, 1560, 1560,
    1560, 1560, 1560, 1560, 1560, 1560, 1560, 0, 0, 0, 0, 0, 0, 0, 0, 0, 0, 0,
    0, 0, 0, 0, 1560, 1560, 1560, 1560, 1560, 1560, 1560, 1560, 1560, 1560,
    1560, 1560, 1560, 1560, 1560, 0, 0, 0, 0, 0, 0, 0, 0, 0, 0, 0, 0, 0, 0, 0,
    1560, 3234, 3220, 3220, 3220, 3220, 3220, 3236, 1560, 3234, 3220, 3220,
    3220, 3236, 1560, 0, 0, 0, 0, 0, 0, 0, 0, 0, 0, 0, 0, 0, 0, 0, 1560, 3216,
    3200, 3200, 3200, 3200, 3200, 3224, 1560, 3216, 3200, 3200, 3200, 3224,
    1560, 0, 0, 0, 0, 0, 0, 0, 0, 0, 0, 0, 0, 0, 0, 0, 1560, 3216, 3200, 3200,
    3200, 3200, 3200, 3224, 1560, 3216, 3200, 3200, 3200, 3224, 1560, 0, 0, 0,
    0, 0, 0, 0, 0, 0, 0, 0, 0, 0, 0, 0, 1560, 3240, 3228, 3228, 3228, 3228,
    3212, 3238, 1560, 3240, 3228, 3228, 3212, 3238, 1560, 0, 0, 0, 0, 0, 0, 0,
    0, 0, 0, 0, 0, 0, 0, 0, 1560, 1560, 1560, 1560, 1560, 1560, 3232, 1560,
    1560, 1560, 1560, 1560, 3232, 1560, 1560, 0, 0, 0, 0, 0, 0, 0, 0, 0, 0, 0,
    0, 0, 0, 0, 1560, 3234, 3220, 3220, 3220, 3220, 3203, 3220, 3220, 3220,
    3220, 3220, 3203, 3236, 1560, 0, 0, 0, 0, 0, 0, 0, 0, 0, 0, 0, 0, 0, 0, 0,
    1560, 3240, 3228, 3228, 3228, 3228, 3228, 3228, 3228, 3228, 3228, 3228,
    3228, 3238, 1560, 0, 0, 0, 0, 0, 0, 0, 0, 0, 0, 0, 0, 0, 0, 0, 1560, 1560,
    1560, 1560, 1560, 1560, 1560, 1560, 1560, 1560, 1560, 1560, 1560, 1560,
    1560, 0, 0, 0, 0, 0, 0, 0, 0, 0, 0, 0, 0, 0, 0, 0, 0, 0, 0, 0, 0, 0, 0, 0,
    0, 0, 0, 0, 0, 0, 0, 0, 0, 0, 0, 0, 0, 0, 0, 0, 0, 0, 0, 0, 0, 0, 0, 0, 0,
    0, 0, 0, 0, 0, 0, 0, 0, 0, 0, 0, 0, 0, 0, 0, 0, 0, 0, 0, 0, 0, 0, 0, 0, 0,
    0, 0, 0, 0, 0, 0, 0, 0, 0, 0, 0, 0, 0, 0, 0, 0, 0, 0, 0, 0, 0, 0, 0, 0, 0,
    0, 0, 0, 0, 0, 0, 0, 0, 0, 0, 0, 0, 0, 0, 0, 0, 0, 0, 0, 0, 0, 0, 0, 0, 0,
    0, 0, 0, 0, 0, 0, 0, 0, 0, 0, 0, 0, 0, 0, 0, 0, 0, 0, 0, 0, 0, 0, 0, 0, 0,
    0, 0, 0, 0, 0, 0, 0, 0, 0, 0, 0, 0, 0, 0, 0, 0, 0, 0, 0, 0, 0, 0, 0, 0, 0,
    0, 0, 0, 0, 0, 0, 0, 0, 0, 0, 0, 0, 0, 0, 0, 0, 0, 0, 0, 0, 0, 0, 0, 0, 0,
    0, 0, 0, 0, 0, 0, 0, 0, 0, 0, 0, 0, 0, 0, 0, 0, 0, 0, 0, 0, 0, 0, 0, 0, 0,
    0, 0, 0, 0, 0, 0, 0, 0, 0, 0, 0, 0, 0, 0, 0, 0, 0, 0, 0, 0, 0, 0, 0, 0, 0,
    0, 0, 0, 0, 0, 0, 0, 0, 0, 0, 0, 0, 0, 0, 0, 0, 0, 0, 0, 0, 0, 0, 0, 0, 0,
    0, 0, 0, 0, 0, 0, 0, 0, 0, 0, 0, 0, 0, 0, 0, 0, 0, 0, 0, 0, 0, 0, 0, 0, 0,
    0, 0, 0, 0, 0, 0, 0, 0, 0, 0, 0, 0, 0, 0, 0, 0, 0, 0, 0, 0, 0, 0, 0, 0, 0,
    0, 0, 0, 0, 0, 0, 0, 0, 0, 0, 0, 0, 0, 0, 0, 0, 0, 0, 0, 0, 0, 0, 0, 0, 0,
    0, 0, 0, 0, 0, 0, 0, 0, 0, 0, 0, 0, 0, 0, 0, 0, 0, 0, 0, 0, 0, 0, 0, 0, 0,
    0, 0, 0, 0, 0, 0, 0, 0, 0, 0, 0, 0, 0, 0, 0, 0, 0, 0, 0, 0, 0, 0, 0, 0, 0,
    0, 0, 0, 0, 0, 0, 0, 0, 0, 0, 0, 0, 0, 0, 0, 0, 0, 0, 0, 0, 0, 0, 0, 0, 0,
    0, 0, 0, 0, 0, 0, 0, 0, 0, 0, 0, 0, 0, 0, 0, 0, 0, 0, 0, 0, 0, 0, 0, 0, 0,
    0, 0, 0, 0, 0, 0, 0, 0, 0, 0, 0, 0, 0, 0, 0, 0, 0, 0, 0, 0, 0, 0, 0, 0, 0,
    0, 0, 0, 0, 0, 0, 0, 0, 0, 0, 0, 0, 0, 0, 0, 0, 0, 0, 0, 0, 0, 0, 0, 0, 0,
    0, 0, 0, 0, 0, 0, 0, 0, 0, 0, 0, 0, 0, 0, 0, 0, 0, 0, 0, 0, 0, 0, 0, 0, 0,
    0, 0, 0, 0, 0, 0, 0, 0, 0, 0, 0, 0, 0, 0, 0, 0, 0, 0, 0, 0, 0, 0, 0, 0, 0,
    0, 0, 0, 0, 0, 0, 0, 0, 0, 0, 0, 0, 0, 0, 0, 0, 0, 0, 0, 0, 0, 0, 0, 0, 0,
    0, 0, 0, 0, 0, 0, 0, 0, 0, 0, 0, 0, 0, 0, 0, 0, 0, 0, 0, 0, 0, 0, 0, 0, 0,
    0, 0, 0, 0, 0, 0, 0, 0, 0, 0, 0, 0, 0, 0, 0, 0, 0, 0, 0, 0, 0, 0, 0, 0, 0,
    0, 0, 0, 0, 0, 0, 0, 0, 0, 0, 0, 0, 0, 0, 0, 0, 0, 0, 0, 0, 0, 0, 0, 0, 0,
    0, 0, 0, 0, 0, 0, 0, 0, 0, 0, 0, 0, 0, 0, 0, 0, 0, 0, 0, 0, 0, 0, 0, 0, 0,
    0, 0, 0, 0, 0, 0, 0, 0, 0, 0, 0, 0, 0, 0, 0, 0, 0, 0, 0, 0, 0, 0, 0, 0, 0,
    0, 0, 0, 0, 0, 0, 0, 0, 0, 0, 0, 0, 0, 0, 0, 0, 0, 0, 0, 0, 0, 0, 0, 0, 0,
    0, 0, 0, 0, 0, 0, 0, 0, 0, 0, 0, 0, 0, 0, 0, 0, 0, 0, 0, 0, 0, 0, 0, 0, 0,
    0, 0, 0, 0, 0, 0, 0, 0, 0, 0, 0, 0, 0, 0, 0, 0, 0, 0, 0, 0, 0, 0, 0, 0, 0,
    0, 0, 0, 0, 0, 0, 0, 0, 0, 0, 0, 0, 0, 0, 0, 0, 0, 0, 0, 0, 0, 0, 0, 0, 0,
    0, 0, 0, 0, 0, 0, 0, 0, 0, 0, 0, 0, 0, 0, 0, 0, 0, 0, 0, 0, 0, 0, 0, 0, 0,
    0, 0, 0, 0, 0, 0, 0, 0, 0, 0, 0, 0, 0, 0, 0, 0, 0, 0, 0, 0, 0, 0, 0, 0, 0,
    0, 0, 0, 0, 0, 0, 0, 0, 0, 0, 0, 0, 0, 0, 0, 0, 0, 0, 0, 0, 0, 0, 0, 0, 0,
    0, 0, 0, 0, 0, 0, 0, 0, 0, 0, 0, 0, 0, 0, 0, 0, 0, 0, 0, 0, 0, 0, 0, 0, 0,
    0, 0, 0, 0, 0, 0, 0, 0, 0, 0, 0, 0, 0, 0, 0, 0, 0, 0, 0, 0, 0, 0, 0, 0, 0,
    0, 0, 0, 0, 0, 0, 0, 0, 0, 0, 0, 0, 0, 0, 0, 0, 0, 0, 0, 0, 0, 0, 0, 0, 0,
    0, 0, 0, 0, 0, 0, 0, 0, 0, 0, 0, 0, 0, 0, 0, 0, 0, 0, 0, 0, 0, 0, 0, 0, 0,
    0, 0, 0, 0, 0, 0, 0, 0, 0, 0, 0, 0, 0, 0, 0, 0, 0, 0, 0, 0, 0, 0, 0, 0, 0,
    0, 0, 0, 0, 0, 0, 0, 0, 0, 0, 0, 0, 0, 0, 0, 0, 0, 0, 0, 0, 0, 0, 0, 0, 0,
    0, 0, 0, 0, 0, 0, 0, 0, 0, 0, 0, 0, 0, 0, 0, 0, 0, 0, 0, 0, 0, 0, 250, 250,
    0, 0, 0, 0, 0, 0, 0, 0, 0, 0, 0, 0, 0, 0, 0, 0, 0, 0, 0, 0, 0, 0, 0, 0, 0,
    0, 0, 0, 0, 235, 0, 0, 0, 0, 0, 0, 0, 0, 0, 0, 0, 0, 0, 0, 0, 0, 0, 0, 0, 0,
    0, 0, 0, 0, 0, 0, 0, 0, 0, 0, 0, 0, 0, 0, 0, 0, 0, 0, 0, 0, 0, 0, 0, 0, 0,
    0, 0, 0, 0, 0, 0, 0, 0, 0, 0, 0, 0, 0, 0, 0, 0, 0, 0, 0, 0, 0, 0, 0, 0, 0,
    0, 0, 0, 0, 0, 0, 0, 0, 0, 0, 0, 0, 0, 0, 0, 0, 0, 0, 0, 0, 0, 0, 0, 0, 0,
    0, 0, 0, 0, 0, 0, 0, 0, 0, 0, 0, 0, 0, 0, 0, 0, 0, 0, 0, 0, 0, 0, 0, 0, 0,
    0, 0, 0, 0, 0, 0, 0, 0, 0, 0, 0, 0, 0, 0, 0, 0, 0, 0, 0, 0, 0, 0, 0, 0, 0,
    0, 0, 0, 0, 0, 0, 0, 0, 0, 0, 0, 0, 0, 0, 0, 0, 0, 0, 0, 0, 0, 0, 0, 0, 0,
    0, 0, 0, 0, 0, 0, 0, 0, 0, 0, 0, 0, 0, 0, 0, 0, 0, 0, 0, 0, 0, 0, 0, 0, 0,
    0, 0, 0, 0, 0, 0, 0, 0, 0, 0, 0, 0, 0, 0, 0, 0, 0, 0, 0, 0, 0, 0, 0, 0, 0,
    0, 0, 0, 0, 0, 0, 0, 0, 0, 0, 0, 0, 0, 0, 0, 0, 0, 0, 0, 0, 0, 0, 0, 0, 0,
    0, 0, 0, 0, 0, 0, 0, 0, 0, 0, 0, 0, 0, 0, 0, 0, 0, 0, 0, 0, 0, 0, 0, 0, 0,
    0, 0, 0, 0, 0, 0, 0, 0, 0, 0, 0, 0, 0, 0, 0, 0, 0, 0, 0, 0, 0, 0, 0, 0, 0,
    0, 0, 0, 0, 0, 0, 0, 0, 0, 0, 0, 0, 0, 0, 0, 0, 0, 0, 0, 0, 0, 0, 0, 0, 0,
    0, 0, 0, 0, 0, 0, 0, 0, 0, 0, 0, 0, 0, 0, 0, 0, 0, 0, 0, 0, 0, 0, 0, 0, 0,
    0, 0, 0, 0, 0, 0, 0, 0, 0, 0, 0, 0, 0, 0, 0, 0, 0, 0, 0, 0, 0, 0, 0, 0, 0,
    0, 0, 0, 0, 0, 0, 0, 0, 0, 0, 0, 0, 0, 0, 0, 0, 0, 0, 0, 0, 0, 0, 0, 0, 0,
    0, 0, 0, 0, 0, 0, 0, 0, 0, 0, 0, 0, 0, 0, 0, 0, 0, 0, 0, 0, 0, 0, 0, 0, 0,
    0, 0, 0, 0, 0, 0, 0, 0, 0, 0, 0, 0, 0, 0, 0, 0, 0, 0, 0, 0, 0, 0, 0, 18, 0,
    0, 0, 0, 0, 0, 0, 228, 0, 0, 0, 0, 0, 0, 0, 0, 0, 0, 0, 0, 0, 0, 0, 0, 0,
    50, 0, 0, 0, 26, 54, 55, 0, 0, 0, 0, 0, 236, 0, 0, 0, 0, 0, 0, 0, 0, 0, 0,
    0, 0, 0, 0, 0, 0, 0, 58, 80, 0, 0, 0, 62, 63, 0, 0, 0, 0, 0, 0, 0, 0, 0, 0,
    0, 0, 0, 0, 0, 0, 0, 0, 0, 0, 0, 0, 0, 0, 88, 0, 0, 108, 0, 0, 228, 0, 242,
    242, 0, 202, 0, 0, 0, 0, 0, 0, 0, 0, 0, 0, 0, 0, 0, 0, 0, 0, 0, 0, 0, 0, 0,
    0, 0, 0, 236, 0, 226, 227, 0, 201, 0, 0, 0, 0, 0, 0, 0, 0, 0, 0, 0, 0, 0, 0,
    0, 0, 0, 0, 0, 0, 0, 0, 0, 0, 0, 0, 234, 228, 0, 201, 0, 0, 0, 0, 0, 0, 0,
    0, 0, 0, 0, 0, 0, 0, 0, 0, 0, 0, 0, 0, 0, 0, 0, 0, 0, 0, 0, 0, 0, 0, 0, 0,
    0, 0, 0, 0, 0, 0, 0, 0, 0, 0, 0, 0, 0, 0, 0, 0, 0, 0, 0, 0, 0, 224, 224, 0,
    0, 0, 0, 224, 0, 0, 0, 0, 0, 0, 0, 0, 0, 0, 0, 0, 0, 0, 0, 0, 0, 11, 0, 0,
    0, 224, 0, 0, 0, 0, 224, 224, 0, 224, 0, 0, 0, 0, 0, 0, 0, 0, 0, 0, 0, 0, 0,
    0, 0, 0, 0, 0, 0, 0, 0, 0, 0, 0, 0, 0, 0, 0, 0, 0, 0, 0, 0, 0, 0, 0, 0, 0,
    0, 0, 0, 0, 0, 0, 0, 0, 0, 0, 0, 0, 0, 0, 0, 0, 0, 0, 0, 0, 0, 0, 0, 0, 0,
    0, 0, 0, 0, 0, 0, 0, 0, 0, 0, 0, 0, 0, 0, 0, 0, 0, 0, 0, 0, 0, 0, 0, 0, 0,
    0, 0, 0, 0, 0, 0, 0, 0, 0, 0, 0, 0, 0, 0, 0, 0, 0, 0, 0, 0, 0, 0, 0, 0, 0,
    0, 0, 0, 0, 0, 0, 0, 0, 0, 0, 0, 0, 0, 0, 0, 0, 0, 0, 0, 0, 0, 0, 0, 0, 0,
    0, 0, 0, 0, 0, 0, 0, 0, 0, 0, 0, 0, 0, 0, 0, 0, 0, 0, 0, 0, 0, 0, 0, 0, 0,
    0, 0, 0, 0, 0, 0, 0, 0, 0, 0, 0, 0, 0, 0, 0, 0, 0, 0, 0, 0, 0, 0, 0, 0, 0,
    0, 0, 0, 0, 0, 0, 0, 0, 0, 0, 0, 0, 0, 0, 0, 0, 0, 0, 0, 0, 0, 0, 0, 0, 0,
    0, 0, 0, 0, 0, 0, 0, 0, 0, 0, 0, 0, 0, 0, 0, 0, 0, 0, 0, 0, 0, 0, 0, 0, 0,
    0, 0, 0, 0, 0, 0, 0, 0, 0, 0, 0, 0, 0, 0, 0, 0, 0, 0, 0, 0, 0, 0, 0, 0, 0,
    0, 0, 0, 0, 0, 0, 0, 0, 0, 0, 0, 0, 0, 0, 0, 0, 0, 0, 0, 0, 0, 0, 0, 0, 0,
    0, 0, 0, 0, 0, 0, 0, 0, 0, 0, 0, 0, 0, 0, 0, 0, 0, 0, 0, 0, 0, 0, 0, 0, 0,
    0, 0, 0, 0, 0, 0, 0, 0, 0, 0, 0, 0, 0, 0, 0, 0, 0, 0, 0, 0, 0, 0, 0, 0, 0,
    0, 0, 0, 0, 0, 0, 0, 0, 0, 0, 0, 0, 0, 0, 0, 0, 0, 0, 0, 0, 0, 0, 0, 0, 0,
    0, 0, 0, 0, 0, 0, 0, 0, 0, 0, 0, 0, 0, 0, 0, 0, 0, 0, 0, 0, 0, 0, 0, 0, 0,
    0, 0, 0, 0, 0, 0, 0, 0, 0, 0, 0, 0, 0, 0, 0, 0, 0, 0, 0, 0, 0, 0, 0, 0, 0,
    0, 0, 0, 0, 0, 0, 0, 0, 0, 0, 0, 0, 0, 0, 0, 0, 0, 0, 0, 0, 0, 0, 0, 0, 0,
    0, 0, 0, 0, 0, 0, 0, 0, 0, 0, 0, 0, 0, 0, 0, 0, 0, 0, 0, 0, 0, 0, 0, 0, 0,
    0, 0, 0, 0, 0, 0, 0, 0, 0, 0, 0, 0, 0, 0, 0, 0, 0, 0, 0, 0, 0, 0, 0, 0, 0,
    0, 0, 0, 0, 0, 0, 0, 0, 0, 0, 0, 0, 0, 0, 0, 0, 0, 0, 0, 0, 0, 0, 0, 0, 0,
    0, 0, 0, 0, 0, 0, 0, 0, 0, 0, 0, 0, 0, 0, 0, 0, 0, 0, 0, 0, 0, 0, 0, 0, 0,
    0, 0, 0, 0, 0, 0, 0, 0, 0, 0, 0, 0, 0, 0, 0, 0, 0, 0, 0, 0, 0, 0, 0, 0, 0,
    0, 0, 0, 0, 0, 0, 0, 0, 0, 0, 0, 0, 0, 0, 0, 0, 0, 0, 0, 0, 0, 0, 0, 0, 0,
    0, 0, 0, 0, 0, 0, 0, 0, 0, 0, 0, 0, 0, 0, 0, 0, 0, 0, 0, 0, 0, 0, 0, 0, 0,
    0, 0, 0, 0, 0, 0, 0, 0, 0, 0, 0, 0, 0, 0, 0, 0, 0, 0, 0, 0, 0, 0, 0, 0, 0,
    0, 0, 0, 0, 0, 0, 0, 0, 0, 0, 0, 0, 0, 0, 0, 0, 0, 0, 0, 0, 0, 0, 0, 0, 0,
    0, 0, 0, 0, 0, 0, 0, 0, 0, 0, 0, 0, 0, 0, 0, 0, 0, 0, 0, 0, 0, 0, 0, 0, 0,
    0, 0, 0, 0, 0, 0, 0, 0, 0, 0, 0, 0, 0, 0, 0, 0, 0, 0, 0, 0, 0, 0, 0, 0, 0,
    0, 0, 0, 0, 0, 0, 0, 0, 0, 0, 0, 0, 0, 0, 0, 0, 0, 0, 0, 0, 0, 0, 0, 0, 0,
    0, 0, 0, 0, 0, 0, 0, 0, 0, 0, 0, 0, 0, 0, 0, 0, 0, 0, 0, 0, 0, 0, 0, 0, 0,
    0, 0, 0, 0, 0, 0, 0, 0, 0, 0, 0, 0, 0, 0, 0, 0, 0, 0, 0, 0, 0, 0, 0, 0, 0,
    0, 0, 0, 0, 0, 0, 0, 0, 0, 0, 0, 0, 0, 0, 0, 0, 0, 0, 0, 0, 0, 0, 0, 0, 0,
    0, 0, 0, 0, 0, 0, 0, 0, 0, 0, 0, 0, 0, 0, 0, 0, 0, 0, 0, 0, 0, 0, 0, 0, 0,
    0, 0, 0, 0, 0, 0, 0, 0, 0, 0, 0, 0, 0, 0, 0, 0, 0, 0, 0, 0, 0, 0, 0, 0, 0,
    0, 0, 0, 0, 0, 0, 0, 0, 0, 0, 0, 0, 0, 0, 0, 0, 0, 0, 0, 0, 0, 0, 0, 0, 0,
    0, 0, 0, 0, 0, 0, 0, 0, 0, 0, 0, 0, 0, 0, 0, 0, 0, 0, 0, 0, 0, 0, 0, 0, 0,
    0, 0, 0, 0, 0, 0, 0, 0, 0, 0, 0, 0, 0, 0, 0, 0, 0, 0, 0, 0, 0, 0, 0, 0, 0,
    0, 0, 0, 0, 0, 0, 0, 0, 0, 0, 0, 0, 0, 0, 0, 0, 0, 0, 0, 0, 0, 0, 0, 0, 0,
    0, 0, 0, 0, 0, 0, 0, 0, 0, 0, 0, 0, 0, 0, 0, 0, 0, 0, 0, 0, 0, 0, 0, 0, 0,
    0, 0, 0, 0, 0, 0, 0, 0, 0, 0, 0, 0, 0, 0, 0, 0, 0, 0, 0, 0, 0, 0, 0, 0, 0,
    0, 0, 0, 0, 0, 0, 0, 0, 0, 0, 0, 0, 0, 0, 0, 0, 0, 0, 0, 0, 0, 0, 0, 0, 0,
    0, 0, 0, 0, 0, 0, 0, 0, 0, 0, 0, 0, 0, 0, 0, 0, 0, 0, 0, 0, 0, 0, 0, 0, 0,
    0, 0, 0, 0, 0, 0, 0, 0, 0, 0, 0, 0, 0, 0, 0, 0, 0, 0, 0, 0, 0, 0, 0, 0, 0,
    0, 0, 0, 0, 0, 0, 0, 0, 0, 0, 0, 0, 0, 0, 0, 0, 0, 0, 0, 0, 0, 0, 0, 0, 0,
    0, 0, 0, 0, 0, 0, 0, 0, 0, 0, 0, 0, 0, 0, 0, 0, 0, 0, 0, 0, 0, 0, 0, 0, 0,
    0, 0, 0, 0, 0, 0, 0, 0, 0, 0, 0, 0, 0, 0, 0, 0, 0, 0, 0, 0, 0, 0, 0, 0, 0,
    0, 0, 0, 0, 0, 0, 0, 0, 0, 0, 0, 0, 0, 0, 0, 0, 0, 0, 0, 0, 0, 0, 0, 0, 0,
    0, 0, 0, 0, 0, 0, 0, 0, 0, 0, 0, 0, 0, 0, 0, 0, 0, 0, 0, 0, 0, 0, 0, 0, 0,
    0, 0, 0, 0, 0, 0, 0, 0, 0, 0, 0, 0, 0, 0, 0, 0, 0, 0, 0, 0, 0, 0, 0, 0, 0,
    0, 0, 0, 0, 0, 0, 0, 0, 0, 0, 0, 0, 0, 0, 0, 0, 0, 0, 0, 0, 0, 0, 0, 0, 0,
    0, 0, 0, 0, 0, 0, 0, 0, 0, 0, 0, 0, 0, 0, 0, 0, 0, 0, 0, 0, 0, 0, 0, 0, 0,
    0, 0, 0, 0, 0, 0, 0, 0, 0, 0, 0, 0, 0, 0, 0, 0, 0, 0, 0, 0, 0, 0, 0, 0, 0,
    0, 0, 0, 0, 0, 0, 0, 0, 0, 0, 0, 0, 0, 0, 0, 0, 0, 0, 0, 0, 0, 0, 0, 0, 0,
    0, 0, 0, 0, 0, 0, 0, 0, 0, 0, 0, 0, 0, 0, 0, 0, 0, 0, 0, 0, 0, 0, 0, 0, 0,
    0, 0, 0, 0, 0, 0, 0, 0, 0, 0, 0, 0, 0, 0, 0, 0, 0, 0, 0, 0, 0, 0, 0, 0, 0
  ],
  "events": [
    null,
    {
      "id": 1,
      "name": "EV001",
      "note": "",
      "pages": [
        {
          "conditions": {
            "actorId": 1,
            "actorValid": false,
            "itemId": 1,
            "itemValid": false,
            "selfSwitchCh": "A",
            "selfSwitchValid": false,
            "switch1Id": 562,
            "switch1Valid": true,
            "switch2Id": 1,
            "switch2Valid": false,
            "variableId": 1,
            "variableValid": false,
            "variableValue": 0
          },
          "directionFix": false,
          "image": {
            "characterIndex": 0,
            "characterName": "",
            "direction": 2,
            "pattern": 0,
            "tileId": 0
          },
          "list": [
            {
              "code": 250,
              "indent": 0,
              "parameters": [
                {
                  "name": "パンパン_濡a01低速(loop)",
                  "volume": 75,
                  "pitch": 90,
                  "pan": 0
                }
              ]
            },
            { "code": 230, "indent": 0, "parameters": [415] },
            { "code": 0, "indent": 0, "parameters": [] }
          ],
          "moveFrequency": 3,
          "moveRoute": {
            "list": [{ "code": 0, "parameters": [] }],
            "repeat": true,
            "skippable": false,
            "wait": false
          },
          "moveSpeed": 3,
          "moveType": 0,
          "priorityType": 1,
          "stepAnime": false,
          "through": false,
          "trigger": 4,
          "walkAnime": false
        },
        {
          "conditions": {
            "actorId": 1,
            "actorValid": false,
            "itemId": 1,
            "itemValid": false,
            "selfSwitchCh": "A",
            "selfSwitchValid": false,
            "switch1Id": 563,
            "switch1Valid": true,
            "switch2Id": 1,
            "switch2Valid": false,
            "variableId": 1,
            "variableValid": false,
            "variableValue": 0
          },
          "directionFix": false,
          "image": {
            "characterIndex": 0,
            "characterName": "",
            "direction": 2,
            "pattern": 0,
            "tileId": 0
          },
          "list": [
            {
              "code": 250,
              "indent": 0,
              "parameters": [
                {
                  "name": "パンパン_渇02中速(loop)",
                  "volume": 65,
                  "pitch": 90,
                  "pan": 0
                }
              ]
            },
            { "code": 230, "indent": 0, "parameters": [610] },
            { "code": 0, "indent": 0, "parameters": [] }
          ],
          "moveFrequency": 3,
          "moveRoute": {
            "list": [{ "code": 0, "parameters": [] }],
            "repeat": true,
            "skippable": false,
            "wait": false
          },
          "moveSpeed": 3,
          "moveType": 0,
          "priorityType": 1,
          "stepAnime": false,
          "through": false,
          "trigger": 4,
          "walkAnime": false
        },
        {
          "conditions": {
            "actorId": 1,
            "actorValid": false,
            "itemId": 1,
            "itemValid": false,
            "selfSwitchCh": "A",
            "selfSwitchValid": false,
            "switch1Id": 564,
            "switch1Valid": true,
            "switch2Id": 1,
            "switch2Valid": false,
            "variableId": 1,
            "variableValid": false,
            "variableValue": 0
          },
          "directionFix": false,
          "image": {
            "characterIndex": 0,
            "characterName": "",
            "direction": 2,
            "pattern": 0,
            "tileId": 0
          },
          "list": [
            {
              "code": 250,
              "indent": 0,
              "parameters": [
                {
                  "name": "パンパン_濡b02中速(loop)",
                  "volume": 80,
                  "pitch": 90,
                  "pan": 0
                }
              ]
            },
            { "code": 230, "indent": 0, "parameters": [327] },
            { "code": 0, "indent": 0, "parameters": [] }
          ],
          "moveFrequency": 3,
          "moveRoute": {
            "list": [{ "code": 0, "parameters": [] }],
            "repeat": true,
            "skippable": false,
            "wait": false
          },
          "moveSpeed": 3,
          "moveType": 0,
          "priorityType": 1,
          "stepAnime": false,
          "through": false,
          "trigger": 4,
          "walkAnime": false
        },
        {
          "conditions": {
            "actorId": 1,
            "actorValid": false,
            "itemId": 1,
            "itemValid": false,
            "selfSwitchCh": "A",
            "selfSwitchValid": false,
            "switch1Id": 565,
            "switch1Valid": true,
            "switch2Id": 1,
            "switch2Valid": false,
            "variableId": 1,
            "variableValid": false,
            "variableValue": 0
          },
          "directionFix": false,
          "image": {
            "characterIndex": 0,
            "characterName": "",
            "direction": 2,
            "pattern": 0,
            "tileId": 0
          },
          "list": [
            {
              "code": 250,
              "indent": 0,
              "parameters": [
                {
                  "name": "擦_濡03高速(loop)",
                  "volume": 90,
                  "pitch": 90,
                  "pan": 0
                }
              ]
            },
            { "code": 230, "indent": 0, "parameters": [350] },
            { "code": 0, "indent": 0, "parameters": [] }
          ],
          "moveFrequency": 3,
          "moveRoute": {
            "list": [{ "code": 0, "parameters": [] }],
            "repeat": true,
            "skippable": false,
            "wait": false
          },
          "moveSpeed": 3,
          "moveType": 0,
          "priorityType": 0,
          "stepAnime": false,
          "through": false,
          "trigger": 4,
          "walkAnime": true
        }
      ],
      "x": 13,
      "y": 11
    },
    {
      "id": 2,
      "name": "ライト",
      "note": "",
      "pages": [
        {
          "conditions": {
            "actorId": 1,
            "actorValid": false,
            "itemId": 1,
            "itemValid": false,
            "selfSwitchCh": "A",
            "selfSwitchValid": false,
            "switch1Id": 1,
            "switch1Valid": false,
            "switch2Id": 1,
            "switch2Valid": false,
            "variableId": 1,
            "variableValid": false,
            "variableValue": 0
          },
          "directionFix": false,
          "image": {
            "tileId": 0,
            "characterName": "sinnyuu",
            "direction": 4,
            "pattern": 1,
            "characterIndex": 0
          },
          "list": [{ "code": 0, "indent": 0, "parameters": [] }],
          "moveFrequency": 3,
          "moveRoute": {
            "list": [{ "code": 0, "parameters": [] }],
            "repeat": true,
            "skippable": false,
            "wait": false
          },
          "moveSpeed": 3,
          "moveType": 0,
          "priorityType": 1,
          "stepAnime": false,
          "through": false,
          "trigger": 0,
          "walkAnime": true
        }
      ],
      "x": 12,
      "y": 8
    },
    null,
    null,
    {
      "id": 5,
      "name": "ライトの部屋の扉",
      "note": "",
      "pages": [
        {
          "conditions": {
            "actorId": 1,
            "actorValid": false,
            "itemId": 1,
            "itemValid": false,
            "selfSwitchCh": "A",
            "selfSwitchValid": false,
            "switch1Id": 1,
            "switch1Valid": false,
            "switch2Id": 1,
            "switch2Valid": false,
            "variableId": 1,
            "variableValid": false,
            "variableValue": 0
          },
          "directionFix": false,
          "image": {
            "tileId": 0,
            "characterName": "!Door1",
            "direction": 2,
            "pattern": 0,
            "characterIndex": 0
          },
          "list": [{ "code": 0, "indent": 0, "parameters": [] }],
          "moveFrequency": 3,
          "moveRoute": {
            "list": [
              { "code": 31, "indent": null },
              { "code": 17, "indent": null },
              { "code": 16, "indent": null },
              { "code": 0, "parameters": [] }
            ],
            "repeat": false,
            "skippable": false,
            "wait": false
          },
          "moveSpeed": 4,
          "moveType": 0,
          "priorityType": 1,
          "stepAnime": true,
          "through": false,
          "trigger": 1,
          "walkAnime": true
        }
      ],
      "x": 14,
      "y": 11
    },
    {
      "id": 6,
      "name": "自宅",
      "note": "",
      "pages": [
        {
          "conditions": {
            "actorId": 1,
            "actorValid": false,
            "itemId": 1,
            "itemValid": false,
            "selfSwitchCh": "A",
            "selfSwitchValid": false,
            "switch1Id": 1,
            "switch1Valid": false,
            "switch2Id": 1,
            "switch2Valid": false,
            "variableId": 1,
            "variableValid": false,
            "variableValue": 0
          },
          "directionFix": false,
          "image": {
            "tileId": 0,
            "characterName": "!Door1",
            "direction": 2,
            "pattern": 0,
            "characterIndex": 0
          },
          "list": [
            {
              "code": 250,
              "indent": 0,
              "parameters": [
                { "name": "Key", "volume": 90, "pitch": 100, "pan": 0 }
              ]
            },
            { "code": 101, "indent": 0, "parameters": ["", 0, 1, 2] },
            {
              "code": 401,
              "indent": 0,
              "parameters": ["It seems the key is locked."]
            },
            { "code": 0, "indent": 0, "parameters": [] }
          ],
          "moveFrequency": 3,
          "moveRoute": {
            "list": [
              { "code": 31, "indent": null },
              { "code": 17, "indent": null },
              { "code": 16, "indent": null },
              { "code": 0, "parameters": [] }
            ],
            "repeat": false,
            "skippable": false,
            "wait": false
          },
          "moveSpeed": 4,
          "moveType": 0,
          "priorityType": 1,
          "stepAnime": true,
          "through": false,
          "trigger": 1,
          "walkAnime": true
        }
      ],
      "x": 20,
      "y": 11
    },
    {
      "id": 7,
      "name": "EV007",
      "note": "",
      "pages": [
        {
          "conditions": {
            "actorId": 1,
            "actorValid": false,
            "itemId": 1,
            "itemValid": false,
            "selfSwitchCh": "A",
            "selfSwitchValid": false,
            "switch1Id": 1,
            "switch1Valid": false,
            "switch2Id": 1,
            "switch2Valid": false,
            "variableId": 1,
            "variableValid": false,
            "variableValue": 0
          },
          "directionFix": false,
          "image": {
            "characterIndex": 0,
            "characterName": "",
            "direction": 2,
            "pattern": 0,
            "tileId": 0
          },
          "list": [
            {
              "code": 223,
              "indent": 0,
              "parameters": [[-255, -255, -255, 0], 1, true]
            },
            { "code": 221, "indent": 0, "parameters": [] },
            { "code": 211, "indent": 0, "parameters": [0] },
            { "code": 101, "indent": 0, "parameters": ["", 0, 1, 2] },
            { "code": 401, "indent": 0, "parameters": ["【Light】"] },
            {
              "code": 401,
              "indent": 0,
              "parameters": ["I wonder how it came to this..."]
            },
            {
              "code": 250,
              "indent": 0,
              "parameters": [
                { "name": "衣擦音06", "volume": 90, "pitch": 100, "pan": 0 }
              ]
            },
            { "code": 101, "indent": 0, "parameters": ["", 0, 0, 2] },
            { "code": 401, "indent": 0, "parameters": ["【Lira】"] },
            {
              "code": 401,
              "indent": 0,
              "parameters": ["Look! I can't wait anymore! Hurry up!"]
            },
            { "code": 223, "indent": 0, "parameters": [[0, 0, 0, 0], 1, true] },
            { "code": 101, "indent": 0, "parameters": ["", 0, 0, 2] },
            { "code": 401, "indent": 0, "parameters": ["【Margaret】"] },
            {
              "code": 401,
              "indent": 0,
              "parameters": ["It's about time to make up your mind."]
            },
            {
              "code": 231,
              "indent": 0,
              "parameters": [1, "ha-remu 1", 0, 0, 0, 0, 100, 100, 255, 0]
            },
            { "code": 101, "indent": 0, "parameters": ["", 0, 0, 2] },
            { "code": 401, "indent": 0, "parameters": ["【Miiru】"] },
            {
              "code": 401,
              "indent": 0,
              "parameters": ["I want to drink semen quickly too!"]
            },
            {
              "code": 241,
              "indent": 0,
              "parameters": [
                { "name": "Scene7", "volume": 65, "pitch": 100, "pan": 0 }
              ]
            },
            {
              "code": 245,
              "indent": 0,
              "parameters": [
                {
                  "name": "02あえぎ(小さめ声多め_2）",
                  "volume": 100,
                  "pitch": 120,
                  "pan": 0
                }
              ]
            },
            { "code": 222, "indent": 0, "parameters": [] },
            { "code": 101, "indent": 0, "parameters": ["", 0, 1, 2] },
            { "code": 401, "indent": 0, "parameters": ["【Light】"] },
            {
              "code": 401,
              "indent": 0,
              "parameters": [
                "Just a while ago, everyone on the lower floor was having a party,\nchatting and eating and drinking."
              ]
            },
            { "code": 101, "indent": 0, "parameters": ["", 0, 1, 2] },
            { "code": 401, "indent": 0, "parameters": ["【Light】"] },
            {
              "code": 401,
              "indent": 0,
              "parameters": [
                "I wonder if the atmosphere changed around the time \\n[1] got drunk."
              ]
            },
            { "code": 101, "indent": 0, "parameters": ["", 0, 1, 2] },
            { "code": 401, "indent": 0, "parameters": ["【Light】"] },
            {
              "code": 401,
              "indent": 0,
              "parameters": [
                "Before I knew it, I was being swept along and ended up in this\nsituation."
              ]
            },
            { "code": 101, "indent": 0, "parameters": ["", 0, 0, 2] },
            { "code": 401, "indent": 0, "parameters": ["【Light】"] },
            {
              "code": 401,
              "indent": 0,
              "parameters": ["Well, it's not like I hate it or anything..."]
            },
            { "code": 101, "indent": 0, "parameters": ["", 0, 0, 2] },
            { "code": 401, "indent": 0, "parameters": ["【Lira】"] },
            { "code": 401, "indent": 0, "parameters": ["What's wrong?"] },
            { "code": 101, "indent": 0, "parameters": ["", 0, 0, 2] },
            { "code": 401, "indent": 0, "parameters": ["【Light】"] },
            {
              "code": 401,
              "indent": 0,
              "parameters": [
                "...It's nothing, but are you really okay with it?"
              ]
            },
            { "code": 101, "indent": 0, "parameters": ["", 0, 0, 2] },
            { "code": 401, "indent": 0, "parameters": ["【Margaret】"] },
            {
              "code": 401,
              "indent": 0,
              "parameters": [
                "Yeah... We discussed it with everyone, and we're fine."
              ]
            },
            { "code": 101, "indent": 0, "parameters": ["", 0, 0, 2] },
            { "code": 401, "indent": 0, "parameters": ["【Miiru】"] },
            {
              "code": 401,
              "indent": 0,
              "parameters": [
                "I don't hate Light, so we decided to share the dick!"
              ]
            },
            { "code": 101, "indent": 0, "parameters": ["", 0, 0, 2] },
            { "code": 401, "indent": 0, "parameters": ["【Light】"] },
            { "code": 401, "indent": 0, "parameters": ["I-Is that so..."] },
            { "code": 101, "indent": 0, "parameters": ["", 0, 1, 2] },
            { "code": 401, "indent": 0, "parameters": ["【Light】"] },
            {
              "code": 401,
              "indent": 0,
              "parameters": [
                "I don't have no reservations, but I'm not capable of enduring the\ncurrent situation. I'll graciously accept it."
              ]
            },
            { "code": 101, "indent": 0, "parameters": ["", 0, 0, 2] },
            { "code": 401, "indent": 0, "parameters": ["【Light】"] },
            {
              "code": 401,
              "indent": 0,
              "parameters": [
                "Good grief, everyone's pussy is soaking wet. Since when did things\nbecome so lewd?"
              ]
            },
            { "code": 101, "indent": 0, "parameters": ["", 0, 0, 2] },
            { "code": 401, "indent": 0, "parameters": ["【Lira】"] },
            {
              "code": 401,
              "indent": 0,
              "parameters": ["Hey! I don't care about that, so hurry up!"]
            },
            { "code": 101, "indent": 0, "parameters": ["", 0, 0, 2] },
            { "code": 401, "indent": 0, "parameters": ["【Light】"] },
            {
              "code": 401,
              "indent": 0,
              "parameters": ["I understand, then I'll start with Lira."]
            },
            { "code": 101, "indent": 0, "parameters": ["", 0, 1, 2] },
            { "code": 401, "indent": 0, "parameters": ["【Light】"] },
            {
              "code": 401,
              "indent": 0,
              "parameters": [
                "Saying that, he roughly thrust his dick into the hot pussy."
              ]
            },
            {
              "code": 231,
              "indent": 0,
              "parameters": [2, "ha-remu 2", 0, 0, 0, 0, 100, 100, 255, 0]
            },
            { "code": 235, "indent": 0, "parameters": [1] },
            {
              "code": 250,
              "indent": 0,
              "parameters": [
                { "name": "挿入02", "volume": 90, "pitch": 100, "pan": 0 }
              ]
            },
            {
              "code": 245,
              "indent": 0,
              "parameters": [
                {
                  "name": "15あえぎ(パターン1）",
                  "volume": 100,
                  "pitch": 120,
                  "pan": 0
                }
              ]
            },
            { "code": 101, "indent": 0, "parameters": ["", 0, 0, 2] },
            { "code": 401, "indent": 0, "parameters": ["【Lira】"] },
            {
              "code": 401,
              "indent": 0,
              "parameters": ["Ah... oh... amazing..."]
            },
            { "code": 101, "indent": 0, "parameters": ["", 0, 0, 2] },
            { "code": 401, "indent": 0, "parameters": ["【Margaret】"] },
            {
              "code": 401,
              "indent": 0,
              "parameters": ["Mm... Lira, you're sneaky..."]
            },
            { "code": 101, "indent": 0, "parameters": ["", 0, 0, 2] },
            { "code": 401, "indent": 0, "parameters": ["【Light】"] },
            {
              "code": 401,
              "indent": 0,
              "parameters": [
                "Next, I'll take care of Margaret, so wait until then."
              ]
            },
            {
              "code": 231,
              "indent": 0,
              "parameters": [1, "ha-remu 3", 0, 0, 0, 0, 100, 100, 255, 0]
            },
            { "code": 235, "indent": 0, "parameters": [2] },
            { "code": 121, "indent": 0, "parameters": [563, 563, 0] },
            { "code": 101, "indent": 0, "parameters": ["", 0, 0, 2] },
            { "code": 401, "indent": 0, "parameters": ["【Lira】"] },
            {
              "code": 401,
              "indent": 0,
              "parameters": ["Ah... oh... wait a moment..."]
            },
            { "code": 101, "indent": 0, "parameters": ["", 0, 0, 2] },
            { "code": 401, "indent": 0, "parameters": ["【Light】"] },
            {
              "code": 401,
              "indent": 0,
              "parameters": [
                "Good grief, after being so eager for it, you're going to say something\nlike that now?"
              ]
            },
            { "code": 101, "indent": 0, "parameters": ["", 0, 0, 2] },
            { "code": 401, "indent": 0, "parameters": ["【Light】"] },
            {
              "code": 401,
              "indent": 0,
              "parameters": [
                "You wanted this, right? I'll make it a mess just as you wished."
              ]
            },
            { "code": 101, "indent": 0, "parameters": ["", 0, 1, 2] },
            { "code": 401, "indent": 0, "parameters": ["【Light】"] },
            {
              "code": 401,
              "indent": 0,
              "parameters": [
                "Lira's pussy is squeezing my dick so tightly, it's hard to believe\nit's her first time."
              ]
            },
            { "code": 101, "indent": 0, "parameters": ["", 0, 1, 2] },
            { "code": 401, "indent": 0, "parameters": ["【Light】"] },
            {
              "code": 401,
              "indent": 0,
              "parameters": [
                "The contrast between the naughty Lira just now and her usual cheerful\nself feels somehow very sinful and exciting."
              ]
            },
            { "code": 101, "indent": 0, "parameters": ["", 0, 0, 2] },
            { "code": 401, "indent": 0, "parameters": ["【Lira】"] },
            {
              "code": 401,
              "indent": 0,
              "parameters": ["That's true, but this kind of thing is no good."]
            },
            { "code": 101, "indent": 0, "parameters": ["", 0, 0, 2] },
            { "code": 401, "indent": 0, "parameters": ["【Miiru】"] },
            {
              "code": 401,
              "indent": 0,
              "parameters": [
                "Lira, what you're saying and your voice don't match at all. It seems\nso convincing that it feels really good."
              ]
            },
            { "code": 101, "indent": 0, "parameters": ["", 0, 1, 2] },
            { "code": 401, "indent": 0, "parameters": ["【Light】"] },
            {
              "code": 401,
              "indent": 0,
              "parameters": [
                "It feels good for me too, so I'll thrust my dick deep inside Lira and\nejaculate."
              ]
            },
            {
              "code": 231,
              "indent": 0,
              "parameters": [2, "ha-remu 4", 0, 0, 0, 0, 100, 100, 255, 0]
            },
            { "code": 235, "indent": 0, "parameters": [1] },
            { "code": 117, "indent": 0, "parameters": [5] },
            { "code": 121, "indent": 0, "parameters": [563, 563, 1] },
            { "code": 251, "indent": 0, "parameters": [] },
            { "code": 246, "indent": 0, "parameters": [5] },
            { "code": 101, "indent": 0, "parameters": ["", 0, 0, 2] },
            { "code": 401, "indent": 0, "parameters": ["【Lira】"] },
            {
              "code": 401,
              "indent": 0,
              "parameters": [
                "Ah... it's amazing... Light's is coming out a lot."
              ]
            },
            {
              "code": 245,
              "indent": 0,
              "parameters": [
                {
                  "name": "02あえぎ(小さめ声多め_2）",
                  "volume": 100,
                  "pitch": 120,
                  "pan": 0
                }
              ]
            },
            { "code": 101, "indent": 0, "parameters": ["", 0, 1, 2] },
            { "code": 401, "indent": 0, "parameters": ["【Light】"] },
            {
              "code": 401,
              "indent": 0,
              "parameters": [
                "This was the most pleasurable ejaculation, releasing every last drop\ninto Lira's pussy. After experiencing something like this..."
              ]
            },
            {
              "code": 231,
              "indent": 0,
              "parameters": [1, "ha-remu 5", 0, 0, 0, 0, 100, 100, 255, 0]
            },
            { "code": 235, "indent": 0, "parameters": [2] },
            { "code": 101, "indent": 0, "parameters": ["", 0, 0, 2] },
            { "code": 401, "indent": 0, "parameters": ["【Margaret】"] },
            {
              "code": 401,
              "indent": 0,
              "parameters": ["That was... amazing, maybe I should go next..."]
            },
            { "code": 101, "indent": 0, "parameters": ["", 0, 0, 2] },
            { "code": 401, "indent": 0, "parameters": ["【Margaret】"] },
            {
              "code": 401,
              "indent": 0,
              "parameters": ["...Light? Your face looks scary... a little..."]
            },
            {
              "code": 250,
              "indent": 0,
              "parameters": [
                { "name": "挿入05", "volume": 90, "pitch": 100, "pan": 0 }
              ]
            },
            {
              "code": 231,
              "indent": 0,
              "parameters": [2, "ha-remu 6", 0, 0, 0, 0, 100, 100, 255, 0]
            },
            { "code": 235, "indent": 0, "parameters": [1] },
            { "code": 101, "indent": 0, "parameters": ["", 0, 0, 2] },
            { "code": 401, "indent": 0, "parameters": ["【Margaret】"] },
            {
              "code": 401,
              "indent": 0,
              "parameters": ["Guh... it's... painful..."]
            },
            { "code": 101, "indent": 0, "parameters": ["", 0, 1, 2] },
            { "code": 401, "indent": 0, "parameters": ["【Light】"] },
            {
              "code": 401,
              "indent": 0,
              "parameters": [
                "Before I knew it, I forcefully pulled Margaret's hips towards me and\ninserted my dick."
              ]
            },
            { "code": 101, "indent": 0, "parameters": ["", 0, 1, 2] },
            { "code": 401, "indent": 0, "parameters": ["【Light】"] },
            {
              "code": 401,
              "indent": 0,
              "parameters": [
                "It's tighter than Lira's pussy, but this feels good in its own way."
              ]
            },
            {
              "code": 231,
              "indent": 0,
              "parameters": [1, "ha-remu 7", 0, 0, 0, 0, 100, 100, 255, 0]
            },
            { "code": 235, "indent": 0, "parameters": [2] },
            {
              "code": 245,
              "indent": 0,
              "parameters": [
                {
                  "name": "17あえぎ(パターン3）",
                  "volume": 100,
                  "pitch": 120,
                  "pan": 0
                }
              ]
            },
            { "code": 121, "indent": 0, "parameters": [563, 563, 0] },
            { "code": 101, "indent": 0, "parameters": ["", 0, 0, 2] },
            { "code": 401, "indent": 0, "parameters": ["【Margaret】"] },
            {
              "code": 401,
              "indent": 0,
              "parameters": ["Nn... nn... ah... this kind of... no good..."]
            },
            { "code": 101, "indent": 0, "parameters": ["", 0, 0, 2] },
            { "code": 401, "indent": 0, "parameters": ["【Miiru】"] },
            {
              "code": 401,
              "indent": 0,
              "parameters": [
                "Wow... Margaret's body is bouncing with each thrust... I wonder if it\ndoesn't hurt?"
              ]
            },
            { "code": 101, "indent": 0, "parameters": ["", 0, 0, 2] },
            { "code": 401, "indent": 0, "parameters": ["【Lira】"] },
            {
              "code": 401,
              "indent": 0,
              "parameters": [
                "At first, I was surprised too, but I quickly got used to it and it\nstarted to feel good... see? \\i[249]"
              ]
            },
            { "code": 101, "indent": 0, "parameters": ["", 0, 0, 2] },
            { "code": 401, "indent": 0, "parameters": ["【Margaret】"] },
            {
              "code": 401,
              "indent": 0,
              "parameters": [
                "Ahh... it's strange... even though it's painful... this kind of\nthing..."
              ]
            },
            { "code": 101, "indent": 0, "parameters": ["", 0, 1, 2] },
            { "code": 401, "indent": 0, "parameters": ["【Light】"] },
            {
              "code": 401,
              "indent": 0,
              "parameters": [
                "I firmly grabbed Margaret, who was trying to escape from my dick, and\nforcefully slammed her hips."
              ]
            },
            { "code": 101, "indent": 0, "parameters": ["", 0, 1, 2] },
            { "code": 401, "indent": 0, "parameters": ["【Light】"] },
            {
              "code": 401,
              "indent": 0,
              "parameters": [
                "After teasing her depths for a while, she began to quietly let out\nlewd sighs."
              ]
            },
            { "code": 101, "indent": 0, "parameters": ["", 0, 0, 2] },
            { "code": 401, "indent": 0, "parameters": ["【Margaret】"] },
            {
              "code": 401,
              "indent": 0,
              "parameters": [
                "Nn... nn... ah... it feels too good... it's making me feel strange...\nsomething like this...--"
              ]
            },
            {
              "code": 231,
              "indent": 0,
              "parameters": [2, "ha-remu 8", 0, 0, 0, 0, 100, 100, 255, 0]
            },
            { "code": 235, "indent": 0, "parameters": [1] },
            { "code": 117, "indent": 0, "parameters": [5] },
            { "code": 121, "indent": 0, "parameters": [563, 563, 1] },
            { "code": 246, "indent": 0, "parameters": [5] },
            { "code": 251, "indent": 0, "parameters": [] },
            { "code": 101, "indent": 0, "parameters": ["", 0, 0, 2] },
            { "code": 401, "indent": 0, "parameters": ["【Margaret】"] },
            { "code": 401, "indent": 0, "parameters": ["Nn... ah... ah..."] },
            {
              "code": 245,
              "indent": 0,
              "parameters": [
                {
                  "name": "02あえぎ(小さめ声多め_2）",
                  "volume": 100,
                  "pitch": 120,
                  "pan": 0
                }
              ]
            },
            { "code": 101, "indent": 0, "parameters": ["", 0, 1, 2] },
            { "code": 401, "indent": 0, "parameters": ["【Light】"] },
            {
              "code": 401,
              "indent": 0,
              "parameters": [
                "I poured my semen into her pussy, causing her body to tremble and her\nbreath to become rough."
              ]
            },
            { "code": 101, "indent": 0, "parameters": ["", 0, 1, 2] },
            { "code": 401, "indent": 0, "parameters": ["【Light】"] },
            {
              "code": 401,
              "indent": 0,
              "parameters": [
                "It feels like I've made Margaret submit, and it's giving me an\nindescribable sense of exhilaration."
              ]
            },
            {
              "code": 231,
              "indent": 0,
              "parameters": [1, "ha-remu 9", 0, 0, 0, 0, 100, 100, 255, 0]
            },
            { "code": 235, "indent": 0, "parameters": [2] },
            { "code": 101, "indent": 0, "parameters": ["", 0, 0, 2] },
            { "code": 401, "indent": 0, "parameters": ["【Lira】"] },
            {
              "code": 401,
              "indent": 0,
              "parameters": [
                "Margaret-chan seems to be feeling really good, but it doesn't seem\nlike she can hear us saying that..."
              ]
            },
            { "code": 101, "indent": 0, "parameters": ["", 0, 0, 2] },
            { "code": 401, "indent": 0, "parameters": ["【Margaret】"] },
            {
              "code": 401,
              "indent": 0,
              "parameters": ["The dick... feels amazing... \\i[249]"]
            },
            { "code": 101, "indent": 0, "parameters": ["", 0, 0, 2] },
            { "code": 401, "indent": 0, "parameters": ["【Miiru】"] },
            {
              "code": 401,
              "indent": 0,
              "parameters": [
                "Hey, hey! Don't have fun with just the three of you, include me too!\nGive me lots of semen!"
              ]
            },
            { "code": 101, "indent": 0, "parameters": ["", 0, 0, 2] },
            { "code": 401, "indent": 0, "parameters": ["【Light】"] },
            {
              "code": 401,
              "indent": 0,
              "parameters": [
                "Sorry, sorry. Look, I'll give you my beloved dick."
              ]
            },
            {
              "code": 245,
              "indent": 0,
              "parameters": [
                {
                  "name": "26フェラ（喘ぎつつ_2）",
                  "volume": 100,
                  "pitch": 130,
                  "pan": 0
                }
              ]
            },
            { "code": 101, "indent": 0, "parameters": ["", 0, 0, 2] },
            { "code": 401, "indent": 0, "parameters": ["【Miiru】"] },
            {
              "code": 401,
              "indent": 0,
              "parameters": [
                "Yay! I've been waiting for this! Mmm \\i[249] slurp \\i[249]"
              ]
            },
            { "code": 101, "indent": 0, "parameters": ["", 0, 0, 2] },
            { "code": 401, "indent": 0, "parameters": ["【Miiru】"] },
            {
              "code": 401,
              "indent": 0,
              "parameters": [
                "Somehow, the taste seems different from usual. Maybe it's because the\nflavors of the two are mixed? But, this taste isn't bad either...\n*smooch*"
              ]
            },
            { "code": 101, "indent": 0, "parameters": ["", 0, 1, 2] },
            { "code": 401, "indent": 0, "parameters": ["【Light】"] },
            {
              "code": 401,
              "indent": 0,
              "parameters": [
                "Miiru becomes absorbed and starts sucking when I present my dick."
              ]
            },
            { "code": 101, "indent": 0, "parameters": ["", 0, 0, 2] },
            { "code": 401, "indent": 0, "parameters": ["【Lira】"] },
            {
              "code": 401,
              "indent": 0,
              "parameters": [
                "Miiru-chan seems absorbed in sucking, but I can understand if she says\nLight's semen is delicious."
              ]
            },
            { "code": 101, "indent": 0, "parameters": ["", 0, 1, 2] },
            { "code": 401, "indent": 0, "parameters": ["【Light】"] },
            {
              "code": 401,
              "indent": 0,
              "parameters": [
                "Miiru's technique is already the best among the three."
              ]
            },
            { "code": 101, "indent": 0, "parameters": ["", 0, 1, 2] },
            { "code": 401, "indent": 0, "parameters": ["【Light】"] },
            {
              "code": 401,
              "indent": 0,
              "parameters": [
                "Moving her small body skillfully, she stimulates my dick more and\nmore."
              ]
            },
            { "code": 101, "indent": 0, "parameters": ["", 0, 0, 2] },
            { "code": 401, "indent": 0, "parameters": ["【Miiru】"] },
            {
              "code": 401,
              "indent": 0,
              "parameters": [
                "*slurp* ... *sigh* ... *kiss* It feels like it's about to come out,\nright? Come on, come on!"
              ]
            },
            {
              "code": 231,
              "indent": 0,
              "parameters": [2, "ha-remu 10", 0, 0, 0, 0, 100, 100, 255, 0]
            },
            { "code": 235, "indent": 0, "parameters": [1] },
            { "code": 117, "indent": 0, "parameters": [4] },
            { "code": 246, "indent": 0, "parameters": [5] },
            { "code": 121, "indent": 0, "parameters": [565, 565, 1] },
            { "code": 251, "indent": 0, "parameters": [] },
            { "code": 101, "indent": 0, "parameters": ["", 0, 1, 2] },
            { "code": 401, "indent": 0, "parameters": ["【Light】"] },
            {
              "code": 401,
              "indent": 0,
              "parameters": [
                "Before I knew it, a large amount of semen gushed out from my dick,\ndyeing the three of them in cloudy liquid."
              ]
            },
            { "code": 101, "indent": 0, "parameters": ["", 0, 0, 2] },
            { "code": 401, "indent": 0, "parameters": ["【Miiru】"] },
            {
              "code": 401,
              "indent": 0,
              "parameters": ["Ehehe, it came out, it came out! *slurp* *kiss*"]
            },
            { "code": 101, "indent": 0, "parameters": ["", 0, 1, 2] },
            { "code": 401, "indent": 0, "parameters": ["【Light】"] },
            {
              "code": 401,
              "indent": 0,
              "parameters": [
                "*sigh*... I got so excited that I ended up ejaculating one after\nanother, but I want to take a breather soon."
              ]
            },
            { "code": 101, "indent": 0, "parameters": ["", 0, 1, 2] },
            { "code": 401, "indent": 0, "parameters": ["【Light】"] },
            {
              "code": 401,
              "indent": 0,
              "parameters": [
                "Just as I tried to distance myself a little from the three, my dick\nwas suddenly grabbed. When I shifted my gaze, Margaret was firmly\ngripping my dick."
              ]
            },
            { "code": 101, "indent": 0, "parameters": ["", 0, 0, 2] },
            { "code": 401, "indent": 0, "parameters": ["【Margaret】"] },
            {
              "code": 401,
              "indent": 0,
              "parameters": [
                "I made a mistake earlier, but I'll be fine this time. I'll make you\npant and gasp."
              ]
            },
            { "code": 101, "indent": 0, "parameters": ["", 0, 0, 2] },
            { "code": 401, "indent": 0, "parameters": ["【Lira】"] },
            {
              "code": 401,
              "indent": 0,
              "parameters": [
                "Margaret-chan, that's not fair! If we're going in order, then it's my\nturn next, right? I'm still not satisfied yet!"
              ]
            },
            { "code": 101, "indent": 0, "parameters": ["", 0, 0, 2] },
            { "code": 401, "indent": 0, "parameters": ["【Miiru】"] },
            {
              "code": 401,
              "indent": 0,
              "parameters": [
                "Hey! What are you resting for! Hurry up and ejaculate, let your semen\ngo *splash* *splash*!"
              ]
            },
            { "code": 101, "indent": 0, "parameters": ["", 0, 0, 2] },
            { "code": 401, "indent": 0, "parameters": ["【Light】"] },
            { "code": 401, "indent": 0, "parameters": ["H-ha...haha..."] },
            { "code": 101, "indent": 0, "parameters": ["", 0, 1, 2] },
            { "code": 401, "indent": 0, "parameters": ["【Light】"] },
            {
              "code": 401,
              "indent": 0,
              "parameters": [
                "In this situation, I have no choice but to prepare myself."
              ]
            },
            { "code": 101, "indent": 0, "parameters": ["", 0, 1, 2] },
            { "code": 401, "indent": 0, "parameters": ["【Light】"] },
            {
              "code": 401,
              "indent": 0,
              "parameters": [
                "It's not like my erection subsided just because I got tired. If it's\nokay with you, I'll go all the way until the end."
              ]
            },
            { "code": 221, "indent": 0, "parameters": [] },
            { "code": 117, "indent": 0, "parameters": [6] },
            { "code": 101, "indent": 0, "parameters": ["", 0, 1, 2] },
            { "code": 401, "indent": 0, "parameters": ["【Light】"] },
            {
              "code": 401,
              "indent": 0,
              "parameters": [
                "After that, when I looked outside the window, the sun was already\ntilting, so it's been almost a full day since the other night."
              ]
            },
            { "code": 101, "indent": 0, "parameters": ["", 0, 1, 2] },
            { "code": 401, "indent": 0, "parameters": ["【Light】"] },
            {
              "code": 401,
              "indent": 0,
              "parameters": [
                "I'm surprised by my own sexual desire to continue the act so\npassionately like this."
              ]
            },
            { "code": 242, "indent": 0, "parameters": [8] },
            { "code": 101, "indent": 0, "parameters": ["", 0, 0, 2] },
            { "code": 401, "indent": 0, "parameters": ["【Lira】"] },
            {
              "code": 401,
              "indent": 0,
              "parameters": ["Hey, hurry up and give me your semen!"]
            },
            { "code": 101, "indent": 0, "parameters": ["", 0, 0, 2] },
            { "code": 401, "indent": 0, "parameters": ["【Margaret】"] },
            {
              "code": 401,
              "indent": 0,
              "parameters": [
                "If you understand that I still want your pussy, then hurry up and\ninsert it."
              ]
            },
            { "code": 117, "indent": 0, "parameters": [3] },
            { "code": 101, "indent": 0, "parameters": ["", 0, 0, 2] },
            { "code": 401, "indent": 0, "parameters": ["【Miiru】"] },
            {
              "code": 401,
              "indent": 0,
              "parameters": [
                "*burp*... My stomach is already full, but I still want more."
              ]
            },
            { "code": 101, "indent": 0, "parameters": ["", 0, 1, 2] },
            { "code": 401, "indent": 0, "parameters": ["【Light】"] },
            {
              "code": 401,
              "indent": 0,
              "parameters": [
                "I turn back to them once again, and they all have such lewd\nexpressions on their faces..."
              ]
            },
            { "code": 101, "indent": 0, "parameters": ["", 0, 1, 2] },
            { "code": 401, "indent": 0, "parameters": ["【Light】"] },
            {
              "code": 401,
              "indent": 0,
              "parameters": [
                "But, I love them so much that I thought it would be nice if these\nsweet and slightly tough days could continue on forever."
              ]
            },
            { "code": 101, "indent": 0, "parameters": ["", 0, 1, 2] },
            { "code": 401, "indent": 0, "parameters": ["..."] },
            { "code": 211, "indent": 0, "parameters": [1] },
            { "code": 101, "indent": 0, "parameters": ["", 0, 1, 2] },
            { "code": 401, "indent": 0, "parameters": ["..."] },
            { "code": 201, "indent": 0, "parameters": [0, 47, 2, 10, 6, 0] },
            { "code": 222, "indent": 0, "parameters": [] },
            { "code": 0, "indent": 0, "parameters": [] }
          ],
          "moveFrequency": 3,
          "moveRoute": {
            "list": [{ "code": 0, "parameters": [] }],
            "repeat": true,
            "skippable": false,
            "wait": false
          },
          "moveSpeed": 3,
          "moveType": 0,
          "priorityType": 0,
          "stepAnime": false,
          "through": false,
          "trigger": 3,
          "walkAnime": true
        }
      ],
      "x": 13,
      "y": 9
    },
    null,
    null,
    null,
    {
      "id": 11,
      "name": "EV011",
      "note": "",
      "pages": [
        {
          "conditions": {
            "actorId": 1,
            "actorValid": false,
            "itemId": 1,
            "itemValid": false,
            "selfSwitchCh": "A",
            "selfSwitchValid": false,
            "switch1Id": 1,
            "switch1Valid": false,
            "switch2Id": 1,
            "switch2Valid": false,
            "variableId": 1,
            "variableValid": false,
            "variableValue": 0
          },
          "directionFix": false,
          "image": {
            "tileId": 0,
            "characterName": "hiro1 h",
            "direction": 6,
            "pattern": 1,
            "characterIndex": 0
          },
          "list": [{ "code": 0, "indent": 0, "parameters": [] }],
          "moveFrequency": 3,
          "moveRoute": {
            "list": [{ "code": 0, "parameters": [] }],
            "repeat": true,
            "skippable": false,
            "wait": false
          },
          "moveSpeed": 3,
          "moveType": 0,
          "priorityType": 1,
          "stepAnime": false,
          "through": false,
          "trigger": 0,
          "walkAnime": true
        }
      ],
      "x": 10,
      "y": 8
    },
    {
      "id": 12,
      "name": "EV012",
      "note": "",
      "pages": [
        {
          "conditions": {
            "actorId": 1,
            "actorValid": false,
            "itemId": 1,
            "itemValid": false,
            "selfSwitchCh": "A",
            "selfSwitchValid": false,
            "switch1Id": 1,
            "switch1Valid": false,
            "switch2Id": 1,
            "switch2Valid": false,
            "variableId": 1,
            "variableValid": false,
            "variableValue": 0
          },
          "directionFix": false,
          "image": {
            "tileId": 0,
            "characterName": "hiro1 h",
            "direction": 6,
            "pattern": 1,
            "characterIndex": 4
          },
          "list": [{ "code": 0, "indent": 0, "parameters": [] }],
          "moveFrequency": 3,
          "moveRoute": {
            "list": [{ "code": 0, "parameters": [] }],
            "repeat": true,
            "skippable": false,
            "wait": false
          },
          "moveSpeed": 3,
          "moveType": 0,
          "priorityType": 1,
          "stepAnime": false,
          "through": false,
          "trigger": 0,
          "walkAnime": true
        }
      ],
      "x": 10,
      "y": 7
    },
    {
      "id": 13,
      "name": "EV013",
      "note": "",
      "pages": [
        {
          "conditions": {
            "actorId": 1,
            "actorValid": false,
            "itemId": 1,
            "itemValid": false,
            "selfSwitchCh": "A",
            "selfSwitchValid": false,
            "switch1Id": 1,
            "switch1Valid": false,
            "switch2Id": 1,
            "switch2Valid": false,
            "variableId": 1,
            "variableValid": false,
            "variableValue": 0
          },
          "directionFix": false,
          "image": {
            "tileId": 0,
            "characterName": "hiro3 h",
            "direction": 6,
            "pattern": 1,
            "characterIndex": 4
          },
          "list": [{ "code": 0, "indent": 0, "parameters": [] }],
          "moveFrequency": 3,
          "moveRoute": {
            "list": [{ "code": 0, "parameters": [] }],
            "repeat": true,
            "skippable": false,
            "wait": false
          },
          "moveSpeed": 3,
          "moveType": 0,
          "priorityType": 1,
          "stepAnime": false,
          "through": false,
          "trigger": 0,
          "walkAnime": true
        }
      ],
      "x": 10,
      "y": 9
    },
    null,
    null,
    null,
    null,
    null,
    null,
    null,
    null,
    null,
    null,
    null
  ]
}
